{"noMoreComments": true, "cursorEnd": 0, "id": "14516", "comments": [{"postBy": {"location": "\u53f0\u7063", "utc": 1415696930000, "level": 0, "avatar": "http://filestoresg1.beetalkmobile.com:8081/file/3301627812606557442", "name": "\u5c0f\u80d6\u59b9\ud83e\udd19\ud83c\udffb"}, "content": "\u6211\u60f3\u6253loooool\ud83d\ude2b", "urls": [], "replies": {"first": [], "last": [], "noMoreReplies": true}, "images": [], "id": 75672}, {"postBy": {"location": "", "utc": 1415699044000, "level": 0, "avatar": "http://filestoresg1.beetalkmobile.com:8081/file/99495908712042185", "name": "Owen Frank"}, "content": "\u6211\u4e5f\u662f\u5361\u572899% \u6709\u6642\u9084\u6703\u8df3\u56de0%", "urls": [], "replies": {"first": [{"content": "\u5404\u7a2e\u751f\u6c23\ud83d\ude21", "reply": "", "id": 42168, "name": "\u5c0f\u80d6\u59b9\ud83e\udd19\ud83c\udffb"}, {"content": "\u5225\u751f\u6c23\u4e86 \u7528\u624b\u52d5\u66f4\u65b0\u5427", "reply": "\u5c0f\u80d6\u59b9\ud83e\udd19\ud83c\udffb", "id": 42576, "name": "Owen Frank"}], "last": [], "noMoreReplies": true}, "images": [], "id": 75881}, {"postBy": {"location": "", "utc": 1415700501000, "level": 0, "avatar": "http://filestoresg1.beetalkmobile.com:8081/file/3956318818377000126", "name": "."}, "content": "\u4e0d\u662f\u5f88\u6b63\u5e38\u55ce\u3002", "urls": [], "replies": {"first": [], "last": [], "noMoreReplies": true}, "images": [], "id": 76031}, {"postBy": {"location": "Taipei City,Taiwan", "utc": 1415700985000, "level": 0, "avatar": "http://filestoresg1.beetalkmobile.com:8081/file/231761662962805021", "name": "taichiu727"}, "content": "\u53ef\u4ee5\u8a66\u624b\u52d5\u66f4\u65b0", "urls": [], "replies": {"first": [], "last": [], "noMoreReplies": true}, "images": [], "id": 76084}, {"postBy": {"location": "\u65b0\u5316\u5340\u00b7\u53f0\u7063", "utc": 1415701051000, "level": 0, "avatar": "http://filestoresg1.beetalkmobile.com:8081/file/5643399564814009088", "name": "\u3002"}, "content": "\u53ef\u4ee5\u624b\u52d5\u66f4\u65b0\u8a66\u8a66", "urls": [], "replies": {"first": [], "last": [], "noMoreReplies": true}, "images": [], "id": 76089}, {"postBy": {"location": "\u53f0\u7063", "utc": 1415702809000, "level": 0, "avatar": "http://filestoresg1.beetalkmobile.com:8081/file/3301627812606557442", "name": "\u5c0f\u80d6\u59b9\ud83e\udd19\ud83c\udffb"}, "content": "\u5df2\u4e0b\u8f09\u624b\u52d5\u66f4\u65b0 \u7121\u53cd\u61c9\ud83d\ude2d", "urls": [], "replies": {"first": [], "last": [], "noMoreReplies": true}, "images": [], "id": 76178}, {"postBy": {"location": "\u694a\u6885\u5e02\u00b7\u53f0\u7063", "utc": 1415704125000, "level": 0, "avatar": "http://filestoresg1.beetalkmobile.com:8081/file/-4052143449454681868", "name": "\u9119\u4eba \u3002"}, "content": "\u9a5a\u8a1d\u3002\u6211\u8981\u8d95\u7dca\u958blol\u770b\u770b \uff01", "urls": [], "replies": {"first": [], "last": [], "noMoreReplies": true}, "images": [], "id": 76248}, {"postBy": {"location": "\u53f0\u7063", "utc": 1415704262000, "level": 0, "avatar": "http://filestoresg1.beetalkmobile.com:8081/file/3301627812606557442", "name": "\u5c0f\u80d6\u59b9\ud83e\udd19\ud83c\udffb"}, "content": "\u54c8\u54c8\uff0c\u61a4\u6012\u522alool\ud83d\ude02\ud83d\ude02", "urls": [], "replies": {"first": [], "last": [], "noMoreReplies": true}, "images": [], "id": 76264}, {"postBy": {"location": "\u53f0\u4e2d\u5e02,\u53f0\u7063", "utc": 1415704799000, "level": 0, "avatar": "http://filestoresg1.beetalkmobile.com:8081/file/17270030060066058", "name": "\u8b1d\u98db\u9b5a"}, "content": "\u53ef\u4ee5\u5148\u53bb\u5b98\u7db2\u8f09\u4fee\u5fa9\u7a0b\u5f0f<br />\u4fee\u5fa9\u5f8c\u518d\u53bb\u4e0b\u8f09\u624b\u52d5\u66f4\u65b0", "urls": [], "replies": {"first": [], "last": [], "noMoreReplies": true}, "images": [], "id": 76328}, {"postBy": {"location": "", "utc": 1415704992000, "level": 0, "avatar": "http://filestoresg1.beetalkmobile.com:8081/file/3956318818377000126", "name": "."}, "content": "\u6709\u4eba\u66f4\u65b0\u6210\u529f\u4e86?", "urls": [], "replies": {"first": [], "last": [], "noMoreReplies": true}, "images": [], "id": 76348}, {"postBy": {"location": "\u53f0\u7063", "utc": 1415706182000, "level": 0, "avatar": "http://filestoresg1.beetalkmobile.com:8081/file/-4052143449454681868", "name": "\u9119\u4eba \u3002"}, "content": "\u5361\u5361 =_= <br />\u600e\u9ebc\u80fd\u5920 \uff5e \u8ab0\u4f86\u544a\u8a34\u6211\u55da\u6e26 \uff5e", "urls": [], "replies": {"first": [], "last": [], "noMoreReplies": true}, "images": [], "id": 76479}]}
