{"noMoreComments": false, "cursorEnd": 22, "id": "376450", "comments": [{"postBy": {"location": "\u5b9c\u862d\u7e23\u00b7\u53f0\u7063", "utc": 1422477596000, "level": 0, "avatar": "http://filestoresg1.beetalkmobile.com:8081/file/-2647793319787117568", "name": "Nick"}, "content": "\u52a0\u6cb9", "urls": [], "replies": {"first": [{"content": "\u8b1d\u8b1d\u4f60", "reply": "", "id": 1851323, "name": "Andrea"}], "last": [], "noMoreReplies": true}, "images": [], "id": 2612386}, {"postBy": {"location": "\u5357\u6295\u7e23\u00b7\u53f0\u7063", "utc": 1422478234000, "level": 0, "avatar": "http://filestoresg1.beetalkmobile.com:8081/file/-7684632994020794122", "name": "\u4f7f\u547d\u5fc5\u9054"}, "content": "\u59b3\u53ea\u662f\u770b\u7684\u66f4\u591a\uff0c\u4e5f\u770b\u5230\u4e86\u81ea\u5df1\u7684\u7f3a\u9ede\uff0c<br />\u91cd\u65b0\u8a8d\u8b58\u81ea\u5df1\uff0c\u8b93\u904e\u53bb\u7684\u4e8b\u4e0d\u518d\u767c\u751f\u3002<br />\u52a0\u6cb9\uff0c\u53ef\u4ee5\u7684!!!", "urls": [], "replies": {"first": [{"content": "\u8b1d\u8b1d\u4f60\uff5e\u6211\u6703\u60f3\u8fa6\u6cd5\u8b93\u81ea\u5df1\u66f4\u597d\u7684\u263a", "reply": "", "id": 1850938, "name": "Andrea"}], "last": [], "noMoreReplies": true}, "images": [], "id": 2612489}, {"postBy": {"location": "\u9ad8\u96c4\u5e02\u00b7\u53f0\u7063", "utc": 1422479228000, "level": 0, "avatar": "http://filestoresg1.beetalkmobile.com:8081/file/8090599089688496075", "name": "\u2651\u59dc\u592a\u516c\u91e3\u8766"}, "content": "\u4e0b\u4e00\u500b\u6703\u66f4\u597d~", "urls": [], "replies": {"first": [{"content": "\u770b\u770b\u56c9", "reply": "", "id": 1851320, "name": "Andrea"}], "last": [], "noMoreReplies": true}, "images": [], "id": 2612656}, {"postBy": {"location": "\u65b0\u7af9\u5e02\u00b7\u53f0\u7063", "utc": 1422479855000, "level": 0, "avatar": "http://filestoresg1.beetalkmobile.com:8081/file/1360083796257801499", "name": "\u9673\u5ef7"}, "content": "\u52a0\u6cb9\u8036\uff01\u4e0b\u4e00\u500b\u6703\u66f4\u597d\uff0c\u771f\u547d\u5929\u5b50\u5c31\u5728\u4e0b\u500b\u8f49\u89d2\u8655\u7b49\u8457\u4f60\u3002", "urls": [], "replies": {"first": [{"content": "\u54c8\uff5e\u770b\u7de3\u4efd\u56c9", "reply": "", "id": 1851291, "name": "Andrea"}], "last": [], "noMoreReplies": true}, "images": [], "id": 2612774}, {"postBy": {"location": "\u9ad8\u96c4\u5e02\u00b7\u53f0\u7063", "utc": 1422480622000, "level": 0, "avatar": "http://filestoresg1.beetalkmobile.com:8081/file/-5999084973860619399", "name": "\u5713\u561f\u561f"}, "content": "\u59b3\u7d50\u5a5a\u6642\uff0c\u958b\u4e00\u684c\u524d\u7537\u53cb\u684c\uff0c\u8b93\u4ed6\u5011\u770b\u770b\u59b3\u591a\u5e78\u798f\uff01", "urls": [], "replies": {"first": [{"content": "\u4e0d\u8cf4", "reply": "", "id": 1851295, "name": "Andrea"}], "last": [], "noMoreReplies": true}, "images": [], "id": 2612969}, {"postBy": {"location": "Taiwan", "utc": 1422480689000, "level": 0, "avatar": "http://filestoresg1.beetalkmobile.com:8081/file/7501553328164666472", "name": "\u80d6\u5b50"}, "content": "\u597d\u5973\u5b69\u90fd\u662f\u5225\u4eba\u7684\u2026\u5230\u5e95\u70ba\u5565\u6211\u9047\u4e0d\u5230\u3002\u9019\u4e9b\u6b7b\u7537\u4e0d\u597d\u73cd\u60dc\u8166\u888b\u6709\u75c5\u3002", "urls": [], "replies": {"first": [{"content": "\u611f\u60c5\u6c92\u6709\u5c0d\u932f \u9806\u5176\u81ea\u7136", "reply": "", "id": 1851301, "name": "Andrea"}], "last": [{"content": "\u4e0d\u5c0d\uff1b\u73fe\u5be6\u9762\u5c31\u662f\u7537\u4eba\u6c92\u6709\u7a69\u5b9a\u6536\u5165\u53ca\u4e8b\u696d\u2026\u5c0d\u7684\u4e5f\u8b8a\u932f\uff1b\u932f\u7684\u66f4\u662f\u932f\u3001\u9806\u5176\u81ea\u7136\u4ecd\u6539\u8b8a\u4e0d\u4e86\u4ec0\u9ebc\uff0c\u6240\u4ee5\u5565\u90fd\u4e0d\u662f\u3002\u59b3\u540c\u610f\u55ce\uff1f", "reply": "", "id": 1854657, "name": "\u80d6\u5b50"}, {"content": "\u6211\u8a8d\u540c\uff0c\u5c31\u7b97\u6709\u7a69\u5b9a\u6536\u5165\u4e5f\u4e0d\u4e00\u5b9a\u6709\u4eba\u8981!\u6bcf\u6708\u8cfa\u4e0d\u5230\u4e09\u842c\uff0c\u4e0d\u7136\u807d\u5230\u5de5\u505a\u662f\u4f5c\u696d\u54e1\u4e5f\u662f~", "reply": "", "id": 1965144, "name": "\u5955\u7fd4"}], "noMoreReplies": true}, "images": [], "id": 2612984}, {"postBy": {"location": "\u53f0\u4e2d\u5e02\u00b7\u53f0\u7063", "utc": 1422481091000, "level": 0, "avatar": "http://filestoresg1.beetalkmobile.com:8081/file/-8999033174311724544", "name": "\u72fc"}, "content": "\u50cf\u524d\u770b\u5427\u5973\u5b69\uff0c\u524d\u65b9\u6709\u4e00\u4f4d\u7537\u4eba\u5728\u7b49\u8457\u59b3\u3002", "urls": [], "replies": {"first": [{"content": "\u4e0d\u5f37\u6c42\u4e86 \u4e00\u500b\u4eba\u4e5f\u8a31\u4e5f\u4e0d\u8cf4", "reply": "", "id": 1851316, "name": "Andrea"}, {"content": "\u5148\u9806\u5176\u81ea\u7136\u5427\uff0c\u6642\u9593\u5230\u4e86\u9084\u662f\u6703\u60f3\u8981\u4eba\u966a\u7684\u3002", "reply": "", "id": 1851328, "name": "\u72fc"}], "last": [], "noMoreReplies": true}, "images": [], "id": 2613096}, {"postBy": {"location": "", "utc": 1422481382000, "level": 0, "avatar": "http://filestoresg1.beetalkmobile.com:8081/file/1450015050176708872", "name": "\u5f88\u4eab\u53d7bee 123"}, "content": "\u65e9\u5b89", "urls": [], "replies": {"first": [{"content": "\u65e9\u5b89", "reply": "", "id": 1851318, "name": "Andrea"}, {"content": "\u6211\u53ef\u4ee5\u8a8d\u8b58\u4f60\u55ce\uff01\uff1f", "reply": "", "id": 1851330, "name": "\u5f88\u4eab\u53d7bee 123"}], "last": [], "noMoreReplies": true}, "images": [], "id": 2613152}, {"postBy": {"location": "\u5b9c\u862d\u7e23\u00b7\u53f0\u7063", "utc": 1422485409000, "level": 0, "avatar": "http://filestoresg1.beetalkmobile.com:8081/file/-4101333395013860087", "name": "\u81ea\u4f86\u4e5f"}, "content": "\u8acb\u6253\u5c0d\u5b57\uff08\u4ed6\uff09\u4e0d\u662f\uff08\u5b83\uff09", "urls": [], "replies": {"first": [{"content": "\u54c8\u54c8\uff5e\u5c0d \u662f\u4ed6", "reply": "", "id": 1851703, "name": "Andrea"}], "last": [{"content": "\u55ef\uff0c\u795d\u798f\u59b3\u3002", "reply": "", "id": 1851721, "name": "\u81ea\u4f86\u4e5f"}, {"content": "\u4f60\u8aaa\u51fa\u6211\u60f3\u8b1b\u7684\u4e86", "reply": "\u81ea\u4f86\u4e5f", "id": 1969712, "name": "Ram"}], "noMoreReplies": true}, "images": [], "id": 2614083}, {"postBy": {"location": "\u6843\u5712\u5e02\u00b7\u53f0\u7063", "utc": 1422485598000, "level": 0, "avatar": "http://filestoresg1.beetalkmobile.com:8081/file/-578290336969051121", "name": "\u8449\u5927\u96c4"}, "content": "\u606d\u559c\u59b3\uff0c\u6210\u9577\u4e86\u22ef\u4e5f\u8a72\u653e\u4e0b\u4e86\uff01\u795d\u59b3\u65e9\u65e5\u9047\u5230\u5c0d\u7684\u4eba\ud83d\ude09", "urls": [], "replies": {"first": [{"content": "\u8b1d\u8b1d\u4f60", "reply": "", "id": 1851729, "name": "Andrea"}, {"content": "\u4e0d\u5ba2\u6c23\ud83d\ude01", "reply": "", "id": 1851948, "name": "\u8449\u5927\u96c4"}], "last": [], "noMoreReplies": true}, "images": [], "id": 2614135}, {"postBy": {"location": "", "utc": 1422485622000, "level": 0, "avatar": "http://filestoresg1.beetalkmobile.com:8081/file/-8976503082195998468", "name": "\u502b"}, "content": "\u52a0\u6cb9\u52a0\u6cb9", "urls": [], "replies": {"first": [{"content": "\ud83d\ude0a", "reply": "", "id": 1851737, "name": "Andrea"}, {"content": "\u773c\u775b\u597d\u6f02\u4eae\u54e6", "reply": "Andrea", "id": 1859298, "name": "\u502b"}], "last": [], "noMoreReplies": true}, "images": [], "id": 2614142}, {"postBy": {"location": "\u65b0\u5317\u5e02\u00b7\u53f0\u7063", "utc": 1422486057000, "level": 0, "avatar": "http://filestoresg1.beetalkmobile.com:8081/file/-2794046131523581073", "name": "\u5442\u67cf"}, "content": "\u5225\u4eba\u8b1b\u7684\u5728\u591a \u2026\u90fd\u6bd4\u4e0d\u4e0a\u81ea\u5df1\u60f3\u7684\u958b \u2026\u6c92\u6709\u4eba\u53ef\u4ee5\u5b8c\u5168\u4f9d\u8cf4\u8457\u53e6\u4e00\u500b \u2026\u7e3d\u662f\u8981\u5b78\u6703\u81ea\u5df1\u6210\u9577 \u2026\u52a0\u6cb9 \u2026\u2026\u2026", "urls": [], "replies": {"first": [{"content": "\u597d\u7684\ud83d\ude0a", "reply": "", "id": 1851733, "name": "Andrea"}, {"content": "\u9019\u9ebc\u65e9\u8d77\ud83d\ude12\ud83d\ude12", "reply": "", "id": 1851861, "name": "\u5442\u67cf"}], "last": [], "noMoreReplies": true}, "images": [], "id": 2614245}, {"postBy": {"location": "\u65b0\u5317\u5e02\u00b7\u53f0\u7063", "utc": 1422486773000, "level": 0, "avatar": "http://filestoresg1.beetalkmobile.com:8081/file/1890623905116728295", "name": "\u9673\u5c0f\u8afa"}, "content": "\u52a0\u6cb9", "urls": [], "replies": {"first": [], "last": [], "noMoreReplies": true}, "images": [], "id": 2614432}, {"postBy": {"location": "\u96f2\u6797\u7e23\u00b7\u53f0\u7063", "utc": 1422494119000, "level": 0, "avatar": "http://filestoresg1.beetalkmobile.com:8081/file/-4344402436963384063", "name": "Ann"}, "content": "\u9858\u6210\u70ba\u966a\u4f34\u59b3\u7684\u65b0\u7537\u53cb\ud83d\ude0b", "urls": [], "replies": {"first": [], "last": [], "noMoreReplies": true}, "images": [], "id": 2617435}, {"postBy": {"location": "\u53f0\u7063", "utc": 1422497083000, "level": 0, "avatar": "http://filestoresg1.beetalkmobile.com:8081/file/2363631143386287648", "name": "\u7fca"}, "content": "\u8b93\u81ea\u5df1\u904e\u5f97\u958b\u5fc3", "urls": [], "replies": {"first": [], "last": [], "noMoreReplies": true}, "images": [], "id": 2619109}, {"postBy": {"location": "\u96f2\u6797\u7e23\u00b7\u53f0\u7063", "utc": 1422497162000, "level": 0, "avatar": "http://filestoresg1.beetalkmobile.com:8081/file/-4885197231443688454", "name": "\u97d3\u5287~\u6211\u7684id\u662f\u6c5f\u5357\u7f8e\u4eba"}, "content": "\u52a0\u6cb9^_^", "urls": [], "replies": {"first": [], "last": [], "noMoreReplies": true}, "images": [], "id": 2619176}, {"postBy": {"location": "", "utc": 1422497413000, "level": 0, "avatar": "http://filestoresg1.beetalkmobile.com:8081/file/467081336672695932", "name": "\u660e\u5fb7"}, "content": "\u52a0\u6cb9", "urls": [], "replies": {"first": [], "last": [], "noMoreReplies": true}, "images": [], "id": 2619341}, {"postBy": {"location": "\u53f0\u4e2d\u5e02\u00b7\u53f0\u7063", "utc": 1422497800000, "level": 0, "avatar": "http://filestoresg1.beetalkmobile.com:8081/file/6580672757625077728", "name": "Vincent"}, "content": "\u96d6\u7136\u53ef\u80fd\u8d70\u7684\u5f88\u6162\uff0c\u4f46\u5343\u842c\u5225\u56de\u982d\u770b\uff0c\u524d\u65b9\u7684\u8def\u4e00\u5b9a\u53c8\u5927\u53c8\u660e\u4eae\u7684\uff5e", "urls": [], "replies": {"first": [], "last": [], "noMoreReplies": true}, "images": [], "id": 2619587}, {"postBy": {"location": "\u9ad8\u96c4\u5e02\u00b7\u53f0\u7063", "utc": 1422497991000, "level": 0, "avatar": "http://filestoresg1.beetalkmobile.com:8081/file/5588480058265656572", "name": "oooooo"}, "content": "\u4fee\u6b63\u81ea\u5df1\u7684\u932f\u8aa4\uff0c\u771f\u547d\u5929\u5b50\u51fa\u73fe\u6642\uff0c\u59b3\u6703\u5e78\u798f\u6eff\u6eff", "urls": [], "replies": {"first": [], "last": [], "noMoreReplies": true}, "images": [], "id": 2619726}]}
