{"noMoreComments": true, "cursorEnd": 0, "id": "31392", "comments": [{"postBy": {"location": "\u65b0\u5317\u5e02\u00b7\u53f0\u7063", "utc": 1417015755000, "level": 0, "avatar": "http://filestoresg1.beetalkmobile.com:8081/file/1492259381370615078", "name": "\u6211\u7684\u6ed1\u677f\u978b\u4e4b\u958b\u5fc3\u5c0f\u74dc"}, "content": "\u597d\u770b", "urls": [], "replies": {"first": [], "last": [], "noMoreReplies": true}, "images": [], "id": 213505}, {"postBy": {"location": "\u65b0\u5317\u5e02\u00b7\u53f0\u7063", "utc": 1417016463000, "level": 0, "avatar": "http://filestoresg1.beetalkmobile.com:8081/file/-3141336605209548237", "name": "\u53c8\u5b85\u53c8\u521d\u3010 \u264d \u3011"}, "content": "\u7d20\u7684\u597d\u7f8e", "urls": [], "replies": {"first": [], "last": [], "noMoreReplies": true}, "images": [], "id": 213652}, {"postBy": {"location": "\u5f70\u5316\u7e23\u00b7\u53f0\u7063", "utc": 1417017058000, "level": 0, "avatar": "http://filestoresg1.beetalkmobile.com:8081/file/3393726203664643585", "name": "\u6b50"}, "content": "\u597d\u6e05\u65b0~", "urls": [], "replies": {"first": [], "last": [], "noMoreReplies": true}, "images": [], "id": 213757}, {"postBy": {"location": "\u53f0\u5357\u5e02\u00b7\u53f0\u7063", "utc": 1417017691000, "level": 0, "avatar": "http://filestoresg1.beetalkmobile.com:8081/file/4563195359636610248", "name": "Dele"}, "content": "\u4e00\u7239 \u6b63\u54e6", "urls": [], "replies": {"first": [], "last": [], "noMoreReplies": true}, "images": [], "id": 213890}, {"postBy": {"location": "\u5f70\u5316\u7e23\u00b7\u53f0\u7063", "utc": 1417018059000, "level": 0, "avatar": "http://filestoresg1.beetalkmobile.com:8081/file/2", "name": "User blocked"}, "content": "\u8def\u4eba\u4e5f\u80fd\u9019\u9ebc\u6b63", "urls": [], "replies": {"first": [], "last": [], "noMoreReplies": true}, "images": [], "id": 213947}, {"postBy": {"location": "\u6843\u5712\u7e23\u00b7\u53f0\u7063", "utc": 1417018518000, "level": 0, "avatar": "http://filestoresg1.beetalkmobile.com:8081/file/5811503896000532009", "name": "\u8449\u5c0f\u9054"}, "content": "\u9806\u773c\u8036", "urls": [], "replies": {"first": [], "last": [], "noMoreReplies": true}, "images": [], "id": 214062}, {"postBy": {"location": "\u9ad8\u96c4\u5e02\u00b7\u53f0\u7063", "utc": 1417056764000, "level": 0, "avatar": "http://filestoresg1.beetalkmobile.com:8081/file/2980806810576028016", "name": "\u8001\u9ed1"}, "content": "\u6b63\u5abd", "urls": [], "replies": {"first": [], "last": [], "noMoreReplies": true}, "images": [], "id": 217415}, {"postBy": {"location": "", "utc": 1417102381000, "level": 0, "avatar": "http://filestoresg1.beetalkmobile.com:8081/file/6683708911119454258", "name": "\u311a -  Wei"}, "content": "\u5c31-\u611b\u6b23\u8cde\u7f8e\u7684-\u4eba-\u4e8b-\u7269-\u63a8(*\u02d8\ufe36\u02d8*)", "urls": [], "replies": {"first": [], "last": [], "noMoreReplies": true}, "images": [], "id": 223823}, {"postBy": {"location": "\u65b0\u5317\u5e02\u00b7\u53f0\u7063", "utc": 1417104217000, "level": 0, "avatar": "http://filestoresg1.beetalkmobile.com:8081/file/-8544509367441452797", "name": "\u80af\u5c3c\u5edd"}, "content": "\u6c34\u54e6", "urls": [], "replies": {"first": [], "last": [], "noMoreReplies": true}, "images": [], "id": 224263}]}
