{"noMoreComments": true, "cursorEnd": 0, "id": "200902", "comments": [{"postBy": {"location": "\u65b0\u7af9\u7e23\u00b7\u53f0\u7063", "utc": 1420339880000, "level": 0, "avatar": "http://filestoresg1.beetalkmobile.com:8081/file/3367545734146092014", "name": "\u5403\u8ca8\u7cd6"}, "content": "\u6211\u5c0d\u8001\u7238\u4f86\u8aaa\u53ea\u662f\u4e00\u500b\u7d2f\u8d05\u800c\u5df2\u5427...", "urls": [], "replies": {"first": [], "last": [], "noMoreReplies": true}, "images": [], "id": 1350647}, {"postBy": {"location": "", "utc": 1420340731000, "level": 0, "avatar": "http://filestoresg1.beetalkmobile.com:8081/file/8072747415496033207", "name": "\u8a79\u6e05\u6797"}, "content": "\u7f3a\u4e4f\u6e9d\u901a\u5427  \u59b3\u9700\u8981\u7684\u662f\u660e\u78ba\u7684\u544a\u8a34\u4ed6\u59b3\u7684\u611f\u89ba", "urls": [], "replies": {"first": [{"content": "\u6211\u73fe\u5728\u9023\u898b\u4ed6\u4e00\u9762\u90fd\u5f88\u96e3", "reply": "", "id": 973284, "name": "\u5403\u8ca8\u7cd6"}], "last": [{"content": "\u6c92\u4f4f\u4e00\u8d77\uff1f  \u5982\u679c\u53ea\u662f\u6642\u9593\u914d\u5408\u4e0d\u4e0a  \u53ef\u4ee5\u7528\u5beb\u7684  \u4e0d\u4e00\u5b9a\u8981\u7528\u8aaa\u7684  \u6216\u662f\u767c\u8a0a\u606f\u7b49\u7b49  \u53ea\u8981\u59b3\u9084\u6709\u5fc3\u60f3\u6e9d\u901a   ", "reply": "\u5403\u8ca8\u7cd6", "id": 973381, "name": "\u8a79\u6e05\u6797"}, {"content": "\u6211\u7238\u5f88\u8a0e\u53ad\u6211", "reply": "\u8a79\u6e05\u6797", "id": 973397, "name": "\u5403\u8ca8\u7cd6"}], "noMoreReplies": true}, "images": [], "id": 1351107}, {"postBy": {"location": "", "utc": 1420341127000, "level": 0, "avatar": "http://filestoresg1.beetalkmobile.com:8081/file/-401709870082623891", "name": "\u7279\u5de5\u337f\u7f85\u5c0f\u665f"}, "content": "\u6c92\u6709\u53ea\u662f\u8ca0\u64d4\u7684\u7236\u5973\u95dc\u4fc2\uff0c\u4e0d\u904e\u770b\u4f60\u5beb\u7684\u611f\u89ba\u5169\u9762\uff0c\u4f60\u9700\u8981\u7684\u662f\u7236\u611b\uff1f\u9084\u662f....", "urls": [], "replies": {"first": [{"content": "\u7576\u7136\u662f\u7236\u611b\u56c9", "reply": "", "id": 973292, "name": "\u5403\u8ca8\u7cd6"}], "last": [{"content": "\u6211\u5abd\u4e5f\u53bb\u4e1610\u5e74\u4e86", "reply": "\u7279\u5de5\u337f\u7f85\u5c0f\u665f", "id": 973428, "name": "\u5403\u8ca8\u7cd6"}, {"content": "\u4e0a\u4e00\u8f29\u7684\u554f\u984c\u5c55\u5ef6\u5230\u4e0b\u4e00\u4ee3\u55ce\uff1f", "reply": "", "id": 973475, "name": "\u7279\u5de5\u337f\u7f85\u5c0f\u665f"}], "noMoreReplies": false}, "images": [], "id": 1351359}, {"postBy": {"location": "", "utc": 1420342242000, "level": 0, "avatar": "http://filestoresg1.beetalkmobile.com:8081/file/4103354306252255453", "name": "\u2229__\u2229"}, "content": "\u9019\u7a2e\u554f\u984c\u6211\u60f3\u7238\u7238\u4e00\u5b9a\u6709\u7121\u6cd5\u91cb\u61f7\u7684\u539f\u56e0\u2026<br />\u5982\u679c\u8981\u6539\u8b8a\u95dc\u4fc2\u4e5f\u4e0d\u662f\u6c92\u6709<br />\u53ea\u662f\u904e\u7a0b\u6703\u5f88\u8f9b\u82e6<br />\u6703\u88ab\u7cdf\u8e4b\u548c\u5ffd\u7565\u7684\u611f\u53d7", "urls": [], "replies": {"first": [], "last": [], "noMoreReplies": true}, "images": [], "id": 1352042}, {"postBy": {"location": "\u65b0\u5317\u5e02\u00b7\u53f0\u7063", "utc": 1420344437000, "level": 0, "avatar": "http://filestoresg1.beetalkmobile.com:8081/file/-5969493574170372348", "name": "\u8001\u7070\u4ed4"}, "content": "\u7238\u7238\u53ea\u662f\u4e0d\u5584\u8868\u9054", "urls": [], "replies": {"first": [], "last": [], "noMoreReplies": true}, "images": [], "id": 1353396}, {"postBy": {"location": "", "utc": 1420347090000, "level": 0, "avatar": "http://filestoresg1.beetalkmobile.com:8081/file/6084025551614509615", "name": "1\u30012\u30013\u6728\u982d\u4eba"}, "content": "\u59b3\u662f\u7238\u7238\u4e0a\u8f29\u5b50\u7684\u60c5\u4eba\u600e\u9ebc\u53ef\u80fd\u4e0d\u611b\u59b3\uff0c\u53ea\u662f\u7238\u7238\u6bd4\u8f03\u4e0d\u5584\u65bc\u8868\u9054\u5c0d\u59b3\u7684\u611b\u7f77\u4e86\uff01", "urls": [], "replies": {"first": [], "last": [], "noMoreReplies": true}, "images": [], "id": 1355035}, {"postBy": {"location": "", "utc": 1420347774000, "level": 0, "avatar": "http://filestoresg1.beetalkmobile.com:8081/file/5216200812205864463", "name": "\u5764"}, "content": "\u54c7 \u6200\u7236\u7656\u55ce\uff1f  \u7238\u7238\u90fd\u662f\u611b\u5973\u5152\u7684", "urls": [], "replies": {"first": [{"content": "\u6211\u7238\u4e0d\u53ef\u80fd", "reply": "", "id": 977871, "name": "\u5403\u8ca8\u7cd6"}], "last": [{"content": "\u600e\u9ebc\u4e0d\u4f4f\u4e00\u8d77\u55ce\uff1f", "reply": "", "id": 979990, "name": "\u5764"}, {"content": "\u662f\u5206\u958b\u5c31\u662f\u4e86\u55ce\uff1f", "reply": "", "id": 980004, "name": "\u5764"}], "noMoreReplies": false}, "images": [], "id": 1355550}, {"postBy": {"location": "", "utc": 1420356606000, "level": 0, "avatar": "http://filestoresg1.beetalkmobile.com:8081/file/4597860766813941498", "name": "\u4ec1\u4e0d\u5728"}, "content": "\u6709\u6a5f\u6703\u591a\u966a\u4ed6\u804a\u804a(^_-)", "urls": [], "replies": {"first": [], "last": [], "noMoreReplies": true}, "images": [], "id": 1361121}]}
