{"noMoreComments": true, "cursorEnd": 0, "id": "192445", "comments": [{"postBy": {"location": "", "utc": 1420215648000, "level": 0, "avatar": "http://filestoresg1.beetalkmobile.com:8081/file/-8857285240858346680", "name": "\u5de5\u85e4\u6fa4\u4e5f"}, "content": "\u53ef\u4ee5\uff0c\u4f46\u4f60\u4e5f\u5f88\u7f8e\u963f", "urls": [], "replies": {"first": [{"content": "\u8ddf\u9019\u88e1\u7684\u773e\u5973\u795e\u76f8\u6bd4\uff0c\u5dee\u5f97\u9060\u4e86\u256e(\u256f_\u2570)\u256d", "reply": "", "id": 929244, "name": "Vivian"}], "last": [{"content": "\u9019\u8ddf\u5e7e\u5e74\u6b21\u6c92\u95dc\u4fc2\u5537\uff5e\u7de3\u4efd\u7de3\u4efd", "reply": "", "id": 929956, "name": "Vivian"}, {"content": "\u59ca\u59ca\uff0c\u8981\u4ecb\u7d39\u55ce", "reply": "Vivian", "id": 929986, "name": "\u5de5\u85e4\u6fa4\u4e5f"}], "noMoreReplies": false}, "images": [], "id": 1293917}]}
