{"noMoreComments": false, "cursorEnd": 20, "id": "487898", "comments": [{"postBy": {"location": "\u5f70\u5316\u7e23\u00b7\u53f0\u7063", "utc": 1423800803000, "level": 0, "avatar": "http://filestoresg1.beetalkmobile.com:8081/file/-5896165180587120100", "name": "\u67ef\u80b2\u6c11"}, "content": "\u52a0\u53b2\u5bb3\uff01", "urls": [], "replies": {"first": [{"content": "\u5927\u54e5\u4e5f\u5f88\u5229\u5bb3\u311a", "reply": "", "id": 2605593, "name": "\u817f\u5728\u9178\uff0c\u7121\u529b"}], "last": [], "noMoreReplies": true}, "images": [], "id": 3466427}, {"postBy": {"location": "\u53f0\u5317\u5e02\u00b7\u53f0\u7063", "utc": 1423850640000, "level": 0, "avatar": "http://filestoresg1.beetalkmobile.com:8081/file/-5315038104933470202", "name": "\ud83e\udddc\ud83c\udffb\u200d\u2640\ufe0f"}, "content": "\u55ae\u65e5110km<br />\u4f46\u662f\u90a3\u662f\u597d\u4e45\u4ee5\u524d\u4e86\u54c8\u54c8", "urls": [], "replies": {"first": [{"content": "\u6c92\u95dc\u4fc2\uff0c\u6162\u6162\u57f9\u990a\u5427\uff01\u9084\u662f\u6703\u4e00\u65e5\u767eK\u7684", "reply": "", "id": 2605575, "name": "\u817f\u5728\u9178\uff0c\u7121\u529b"}, {"content": "\u73fe\u5728\u6703\u66f4\u53b2\u5bb3", "reply": "", "id": 5325276, "name": "\u80d6\u80d6"}], "last": [], "noMoreReplies": true}, "images": [], "id": 3512167}, {"postBy": {"location": "\u53f0\u5317\u5e02\u00b7\u53f0\u7063", "utc": 1423960712000, "level": 0, "avatar": "http://filestoresg1.beetalkmobile.com:8081/file/-8317333772374836186", "name": "\u7fce\u7fce"}, "content": "\u6211\u9a0e\u9f61\u5169\u500b\u6708 \u53ea\u6700\u9060\u9a0e\u904e78\u2026", "urls": [], "replies": {"first": [{"content": "\u6c92\u95dc\u4fc2\uff0c\u6162\u6162\u4f86", "reply": "", "id": 2605368, "name": "\u817f\u5728\u9178\uff0c\u7121\u529b"}, {"content": "\u7b97\u5f88\u53b2\u5bb3\u4e86", "reply": "", "id": 5325250, "name": "\u80d6\u80d6"}], "last": [], "noMoreReplies": true}, "images": [], "id": 3584415}, {"postBy": {"location": "\u9ad8\u96c4\u5e02\u00b7\u53f0\u7063", "utc": 1423984314000, "level": 0, "avatar": "http://filestoresg1.beetalkmobile.com:8081/file/6384989367711847489", "name": "\u4e09\u96bb\u5c0f\u82f1\u52c7"}, "content": "100k \u6b63\u5728\u8a2d\u6cd5\u7a81\u7834\u4e2d", "urls": [], "replies": {"first": [{"content": "\u53ef\u4ee5\u7684\u4e00\u65e5\u58be\u4e01\uff0c\u59b3\u7684\u8eca\u8ddf\u6211\u5011\u7684\u5973\u6027\u8eca\u53cb\u540c\u4e00\u53f0\u5537", "reply": "", "id": 2605401, "name": "\u817f\u5728\u9178\uff0c\u7121\u529b"}], "last": [{"content": "\u9084\u597d\uff0c\u5927\u5bb6\u51fa\u4f86\u9a0e\u8eca\u6c92\u6709\u5728\u6bd4\u5feb\u7684\uff0c\u662f\u4eab\u53d7\u5927\u5bb6\u4e00\u8d77\u51fa\u904a\u4e00\u8d77\u9a0e\u8eca\u7684\u6a02\u8da3", "reply": "", "id": 3174184, "name": "\u817f\u5728\u9178\uff0c\u7121\u529b"}, {"content": "\u53ef\u4ee5\u627e\u670b\u53cb\u4e00\u8d77\u9a0e\u7df4\u7fd2", "reply": "", "id": 5325231, "name": "\u80d6\u80d6"}], "noMoreReplies": false}, "images": [], "id": 3602686}, {"postBy": {"location": "\u5f70\u5316\u7e23\u00b7\u53f0\u7063", "utc": 1424001814000, "level": 0, "avatar": "http://filestoresg1.beetalkmobile.com:8081/file/-6316625031040848127", "name": "Jin"}, "content": "\u6700\u8fd1\u9031\u672b\u90fd\u9a0e80~100k\u9a0e\u5927\u69824\u5c0f\u6642\uff0c<br />\u66fe\u7d93\u9a0e\u904e150k", "urls": [], "replies": {"first": [{"content": "\u5229\u5bb3!\u4e00\u8d77\u52a0\u6cb9", "reply": "", "id": 2605427, "name": "\u817f\u5728\u9178\uff0c\u7121\u529b"}], "last": [{"content": "\u5e0c\u671b\u6211\u4e5f\u53ef\u4ee5\u4e00\u65e5200><", "reply": "", "id": 2605707, "name": "Jin"}, {"content": "\u6709\u671d\u4e00\u65e5\u53ef\u4ee5\u7684", "reply": "", "id": 3174200, "name": "\u817f\u5728\u9178\uff0c\u7121\u529b"}], "noMoreReplies": true}, "images": [], "id": 3617250}, {"postBy": {"location": "\u53f0\u5317\u5e02\u00b7\u53f0\u7063", "utc": 1424004569000, "level": 0, "avatar": "http://filestoresg1.beetalkmobile.com:8081/file/-3861536508393304498", "name": "\u264fJeff Shen\ud83d\udeb5"}, "content": "\u4eca\u5929\u9a0e\uff11\uff11\uff19k", "urls": [], "replies": {"first": [{"content": "\u731b\u5537\uff01", "reply": "", "id": 2605446, "name": "\u817f\u5728\u9178\uff0c\u7121\u529b"}], "last": [{"content": "\u9084\u597d\u5566\uff01\u56e0\u70ba\u7a81\u7136\u4e0b\u96e8\uff0c\u6240\u4ee5\u5c31\u56de\u5bb6\u4e86\n\u4e0d\u7136\u9084\u60f3\u5728\u7e7c\u7e8c\u9a0e\u5462\uff1f", "reply": "\u817f\u5728\u9178\uff0c\u7121\u529b", "id": 2605612, "name": "\u264fJeff Shen\ud83d\udeb5"}, {"content": "\u5929\u7a7a\u4e0d\u505a\u7f8e\uff0c\u6c92\u6cd5\u5ea6\u4eab\u53d7\u9a0e\u8eca\u6a02\u8da3\u5427\uff01", "reply": "", "id": 3174213, "name": "\u817f\u5728\u9178\uff0c\u7121\u529b"}], "noMoreReplies": true}, "images": [], "id": 3619912}, {"postBy": {"location": "\u5c4f\u6771\u7e23\u00b7\u53f0\u7063", "utc": 1424011751000, "level": 0, "avatar": "http://filestoresg1.beetalkmobile.com:8081/file/-1028650301294306066", "name": "\u817f\u5728\u9178\uff0c\u7121\u529b"}, "content": "2\u670811\u865f\u5c0f\u5f1f\u53c8\u4e00\u65e5\u8eca\u57ce\uff0c\u4f86\u56de167\u516c\u91cc", "urls": [], "replies": {"first": [], "last": [], "noMoreReplies": true}, "images": [], "id": 3628036}, {"postBy": {"location": "", "utc": 1424020073000, "level": 0, "avatar": "http://filestoresg1.beetalkmobile.com:8081/file/803741908244120545", "name": "\u505a\u81ea\u5df1 \u83ab\u5fd8\u521d\u8877"}, "content": "160\u5427\ud83d\ude09\u5c31\u6ff1\u6d77\u98a8\u5f88\u8212\u670d\u5c31\u4e00\u76f4\u9a0e\uff0c\u7e5e\u5927\u53f0\u5317\u4e00\u5708", "urls": [], "replies": {"first": [{"content": "\u4e0d\u932f\u5537\uff0c\u55ae\u8eca\u5c31\u662f\u53ef\u4ee5\u770b\u5f88\u591a\u7f8e\u9e97\u7684\u98a8\u666f", "reply": "", "id": 2620699, "name": "\u817f\u5728\u9178\uff0c\u7121\u529b"}], "last": [], "noMoreReplies": true}, "images": [], "id": 3638802}, {"postBy": {"location": "\u9ad8\u96c4\u5e02\u00b7\u53f0\u7063", "utc": 1424060801000, "level": 0, "avatar": "http://filestoresg1.beetalkmobile.com:8081/file/-4125144425712364312", "name": "\u9673\u827e\u8349"}, "content": "\u53bb\u5e74\u65b0\u7389\u9580\u95dc\u22ef\u9ad8\u96c4\u53f0\u5357\u5169\u767eK\u22ef<br />\u4f46\u662f\u771f\u7684\u5f88\u7d2f\u22ef\u22ef", "urls": [], "replies": {"first": [{"content": "\u5927\u5927\u5229\u5bb3\u5537", "reply": "", "id": 3174222, "name": "\u817f\u5728\u9178\uff0c\u7121\u529b"}], "last": [], "noMoreReplies": true}, "images": [], "id": 3662026}, {"postBy": {"location": "\u65b0\u7af9\u7e23\u00b7\u53f0\u7063", "utc": 1424137067000, "level": 0, "avatar": "http://filestoresg1.beetalkmobile.com:8081/file/-3470635937322873341", "name": "YoHsiang"}, "content": "\u4e4b\u524d\u6709\u904e\u4e00\u65e5190\u5de6\u53f3 <br />\u56e0\u70ba\u539f\u5148\u96f2\u6797\u9810\u5b9a\u8981\u4f4f\u7684\u5730\u65b9\u592a\u8352\u6dbc<br />\u786c\u662f\u591a\u9a0e\u4e862 30", "urls": [], "replies": {"first": [{"content": "\u5927\u5927\u662f\u731b\u817f\u5229\u5bb3", "reply": "", "id": 3174231, "name": "\u817f\u5728\u9178\uff0c\u7121\u529b"}], "last": [], "noMoreReplies": true}, "images": [], "id": 3724586}, {"postBy": {"location": "\u65b0\u5317\u5e02\u00b7\u53f0\u7063", "utc": 1424138289000, "level": 0, "avatar": "http://filestoresg1.beetalkmobile.com:8081/file/-3338676952225799168", "name": "Hman"}, "content": "\u9019\u4f4d\u5927\u54e5\u771f\u53b2\u5bb3\uff0c\u6211\u6700\u591a\u677f\u6a4b\u51fa\u767c\u5230\u57fa\u9686\u4e0a\u4e5d\u4efd\u518d\u7e5e\u5317\u6d77\u5cb8\u5f9e\u6de1\u6c34\u56de\u677f\u6a4b\uff0c\u5927\u6982160\u516c\u91cc\u3002", "urls": [], "replies": {"first": [{"content": "\u5176\u5be6\u817f\u529b\u662f\u9a0e\u51fa\u4f86\u7684\u6240\u4ee5\u4e0d\u5fc5\u7fa8\u6155\u4ed6\u4eba\uff0c\u53bb\u4eab\u53d7\u9a0e\u8eca\u6a02\u8da3\u5427\uff01\u4f60\u4e5f\u6703\u6709\u4e00\u5929\u53ef\u4ee5\u78342\u767e", "reply": "", "id": 3174250, "name": "\u817f\u5728\u9178\uff0c\u7121\u529b"}], "last": [], "noMoreReplies": true}, "images": [], "id": 3725498}, {"postBy": {"location": "\u53f0\u5317\u5e02\u00b7\u53f0\u7063", "utc": 1424141636000, "level": 0, "avatar": "http://filestoresg1.beetalkmobile.com:8081/file/3899739046604982765", "name": "EdenLock"}, "content": "\u4e0a\u6b21\u5f9e\u81fa\u5317\u9a0e\u5230\u6843\u5712\u518d\u56de\u4f86  \u5927\u7d04100km  <--(\u56e0\u70ba\u6709\u7e5e\u9ede\u8def  \u6240\u4ee5\u7e3d\u9577\u6bd4\u8f03\u9060", "urls": [], "replies": {"first": [], "last": [], "noMoreReplies": true}, "images": [], "id": 3728470}, {"postBy": {"location": "\u53f0\u5357\u5e02\u00b7\u53f0\u7063", "utc": 1424189007000, "level": 0, "avatar": "http://filestoresg1.beetalkmobile.com:8081/file/-7773551605406120437", "name": "RIP"}, "content": "\u4e94\u65e5\u74b0\u5cf6\u7684\u6700\u5f8c\u3127\u5929\uff0c344k\u3002", "urls": [], "replies": {"first": [{"content": "\u5229\u5bb3\uff0c\u6211\u74b0\u5cf6\u7b2c\u4e00\u6b216\u5929\u7b2c\u4e8c\u6b215\u5929", "reply": "", "id": 3174264, "name": "\u817f\u5728\u9178\uff0c\u7121\u529b"}], "last": [], "noMoreReplies": true}, "images": [], "id": 3775833}, {"postBy": {"location": "\u65b0\u5317\u5e02\u00b7\u53f0\u7063", "utc": 1424189902000, "level": 0, "avatar": "http://filestoresg1.beetalkmobile.com:8081/file/1350250857911893074", "name": "\ud83d\ude08\ud83d\udc02\u9ec3\u5c1a\u744b\u6c34\u725b\ud83d\udc02\ud83d\ude08"}, "content": "\u4e00\u65e5\u5317\u9ad8 360k", "urls": [], "replies": {"first": [{"content": "\u5927\u54e5\u5229\u5bb3\u5537\uff0c\u5c0f\u5f1f\u6211\u4e5f\u5f88\u60f3\u53bb\u4e00\u65e5\u5317\u9ad8\u8aaa", "reply": "", "id": 3174281, "name": "\u817f\u5728\u9178\uff0c\u7121\u529b"}, {"content": "\u662f\u8ddf\u8eca\u53cb\u4e00\u8d77\u53bb\u7684", "reply": "", "id": 3175479, "name": "\ud83d\ude08\ud83d\udc02\u9ec3\u5c1a\u744b\u6c34\u725b\ud83d\udc02\ud83d\ude08"}], "last": [], "noMoreReplies": true}, "images": [], "id": 3777079}, {"postBy": {"location": "\u53f0\u6e7e\u7701\u00b7\u4e2d\u56fd", "utc": 1424193645000, "level": 0, "avatar": "http://filestoresg1.beetalkmobile.com:8081/file/8041007811185421016", "name": "Shang"}, "content": "\u65b0\u7389\u9580\u95dc 155k", "urls": [], "replies": {"first": [], "last": [], "noMoreReplies": true}, "images": [], "id": 3782107}, {"postBy": {"location": "\u53f0\u5357\u5e02\u00b7\u53f0\u7063", "utc": 1424231748000, "level": 0, "avatar": "http://filestoresg1.beetalkmobile.com:8081/file/3098257742051088897", "name": "Basser"}, "content": "\u9023\u7e8c300km\u74b0\u5cf67\u59291000I'm", "urls": [], "replies": {"first": [], "last": [], "noMoreReplies": true}, "images": [], "id": 3806658}, {"postBy": {"location": "", "utc": 1424301868000, "level": 0, "avatar": "http://filestoresg1.beetalkmobile.com:8081/file/3644616069358579261", "name": "story man "}, "content": "120k.>___<", "urls": [], "replies": {"first": [], "last": [], "noMoreReplies": true}, "images": [], "id": 3867816}, {"postBy": {"location": "\u96f2\u6797\u7e23\u00b7\u53f0\u7063", "utc": 1424308602000, "level": 0, "avatar": "http://filestoresg1.beetalkmobile.com:8081/file/-2366450281901822298", "name": "Hans"}, "content": "\u5317\u9ad8", "urls": [], "replies": {"first": [], "last": [], "noMoreReplies": true}, "images": [], "id": 3871851}, {"postBy": {"location": "\u65b0\u5317\u5e02\u00b7\u53f0\u7063", "utc": 1424310252000, "level": 0, "avatar": "http://filestoresg1.beetalkmobile.com:8081/file/-2231198255375246596", "name": "bluebox"}, "content": "\u52a0\u4e0a\u8ff7\u8def\u9b3c\u6253\u7246 \u5927\u7d04100", "urls": [], "replies": {"first": [], "last": [], "noMoreReplies": true}, "images": [], "id": 3873083}]}
