{"noMoreComments": true, "cursorEnd": 0, "id": "326715", "comments": [{"postBy": {"location": "", "utc": 1421861002000, "level": 0, "avatar": "http://filestoresg1.beetalkmobile.com:8081/file/-3872626267531244027", "name": "vicious\u4ec1"}, "content": "\u8c93\u54aa\u8d85\u53ef\u611b~", "urls": [], "replies": {"first": [], "last": [], "noMoreReplies": true}, "images": [], "id": 2242400}, {"postBy": {"location": "", "utc": 1421862981000, "level": 0, "avatar": "http://filestoresg1.beetalkmobile.com:8081/file/6084025551614509615", "name": "1\u30012\u30013\u6728\u982d\u4eba"}, "content": "\u96ea\u767d\u7684\u8c93\u54aa", "urls": [], "replies": {"first": [], "last": [], "noMoreReplies": true}, "images": [], "id": 2243686}]}
