{"noMoreComments": false, "cursorEnd": 20, "id": "19431", "comments": [{"postBy": {"location": "\u53f0\u5357\u5e02\u00b7\u53f0\u7063", "utc": 1416109255000, "level": 0, "avatar": "http://filestoresg1.beetalkmobile.com:8081/file/2993478681891762199", "name": "\u82b3"}, "content": "8\u6708\u7345\u5b50\u6b50   \u54c8\u54c8\u54c8", "urls": [], "replies": {"first": [{"content": "\u6211\u8ddf\u4f60\u540c\u4e00\u5929\u751f\u65e5", "reply": "", "id": 897337, "name": "\u5c0f\u971c"}], "last": [], "noMoreReplies": true}, "images": [], "id": 113591}, {"postBy": {"location": "Nantou County\u00b7Taiwan", "utc": 1416129116000, "level": 0, "avatar": "http://filestoresg1.beetalkmobile.com:8081/file/4919743887762784413", "name": "\u6751\u6751"}, "content": "\u4e03\u6708\u7684\u7345\u5b50\u4e003\u4e00", "urls": [], "replies": {"first": [], "last": [], "noMoreReplies": true}, "images": [], "id": 115668}, {"postBy": {"location": "", "utc": 1416134024000, "level": 0, "avatar": "http://filestoresg1.beetalkmobile.com:8081/file/-6783338030599838975", "name": "\u50bb\u725b"}, "content": "8\u6708\u7345   \uff0co\u578b", "urls": [], "replies": {"first": [], "last": [], "noMoreReplies": true}, "images": [], "id": 116255}, {"postBy": {"location": "\u53f0\u5317\u5e02\u00b7\u53f0\u7063", "utc": 1416138702000, "level": 0, "avatar": "http://filestoresg1.beetalkmobile.com:8081/file/8903906737470703771", "name": "\ud83d\uddff\u674e\u5c0f\u86c7\ud83c\udf34"}, "content": "8\u67082\u65e5 \u8840\u578b A\u578b \u5c6c\u86c7", "urls": [], "replies": {"first": [{"content": "\u6211\u4e5f7/2", "reply": "", "id": 470801, "name": "\u80a5\u7684\u4e0d\u8981\u4e0d\u8981\u7684"}], "last": [{"content": "8/2\u5566 \u6253\u932f", "reply": "", "id": 470809, "name": "\u80a5\u7684\u4e0d\u8981\u4e0d\u8981\u7684"}, {"content": "\u54c8\u54c8\u54c8 \u59b3\u597d\u5440\uff01", "reply": "\u80a5\u7684\u4e0d\u8981\u4e0d\u8981\u7684", "id": 475700, "name": "\ud83d\uddff\u674e\u5c0f\u86c7\ud83c\udf34"}], "noMoreReplies": true}, "images": [], "id": 116803}, {"postBy": {"location": "\u53f0\u5317\u5e02\u00b7\u53f0\u7063", "utc": 1416162729000, "level": 0, "avatar": "http://filestoresg1.beetalkmobile.com:8081/file/6544141477200117297", "name": "Hong-Wei"}, "content": "8\u6708\u7345\u5b50", "urls": [], "replies": {"first": [], "last": [], "noMoreReplies": true}, "images": [], "id": 120519}, {"postBy": {"location": "", "utc": 1416169223000, "level": 0, "avatar": "http://filestoresg1.beetalkmobile.com:8081/file/-3692474501645404173", "name": "Constance"}, "content": "7/30 \u3109\u2026\u2026\u2026\u2026\u7345\u5b50", "urls": [], "replies": {"first": [{"content": "me2", "reply": "", "id": 131062, "name": "Nicki"}], "last": [{"content": "+\uff11", "reply": "", "id": 16066862, "name": "jiun-jen"}, {"content": "\u6211\u4e5f\u662f7/30\u8036\uff01", "reply": "", "id": 21000643, "name": "\u6bdb\u5b69\u4e0d\u6d41\u6d6a"}], "noMoreReplies": false}, "images": ["http://filestoresg1.beetalkmobile.com:8081/file/65bec1aea367bca04625fb085e22e578"], "id": 121024}, {"postBy": {"location": "\u53f0\u5317\u5e02,\u53f0\u7063", "utc": 1416170345000, "level": 0, "avatar": "http://filestoresg1.beetalkmobile.com:8081/file/-3359419236151763968", "name": "\u505c\u6b0a\u5427 \u4e0d\u7528\u4e86"}, "content": "8/14", "urls": [], "replies": {"first": [{"content": "+1", "reply": "", "id": 237604, "name": "J J "}], "last": [{"content": "+1", "reply": "", "id": 11819724, "name": "\u6f58\u51a0\u8ce2"}, {"content": "+1", "reply": "", "id": 15707131, "name": "\u8c50\u540d"}], "noMoreReplies": false}, "images": [], "id": 121076}, {"postBy": {"location": "\u9ad8\u96c4\u5e02\u00b7\u53f0\u7063", "utc": 1416170466000, "level": 0, "avatar": "http://filestoresg1.beetalkmobile.com:8081/file/6907287080210690756", "name": "\u5f64"}, "content": "8/14\u7345\u5b50\u5ea7", "urls": [], "replies": {"first": [{"content": "+1", "reply": "", "id": 237602, "name": "J J "}], "last": [{"content": "\u6211\u4e5f\u662f8.14", "reply": "", "id": 2079487, "name": "\u671d\u7d9c"}, {"content": "+1  \u7da0\u8272\u60c5\u4eba\u7bc0", "reply": "", "id": 55851265, "name": "\u5c0f\u6690"}], "noMoreReplies": false}, "images": [], "id": 121082}, {"postBy": {"location": "\u65b0\u5317\u5e02,\u53f0\u7063", "utc": 1416186616000, "level": 0, "avatar": "http://filestoresg1.beetalkmobile.com:8081/file/6248922604787801346", "name": "Jacky"}, "content": "8/13\u7345\u5b50\ud83d\ude02", "urls": [], "replies": {"first": [{"content": "+1", "reply": "", "id": 375892, "name": "\u7c73"}], "last": [{"content": "+1", "reply": "", "id": 19744666, "name": "\u6c81\u8377\ud83d\udc69\u200d\ud83c\udfeb"}, {"content": "+1", "reply": "", "id": 39755657, "name": "E"}], "noMoreReplies": false}, "images": [], "id": 121733}, {"postBy": {"location": "\u53f0\u5357\u5e02\u00b7\u53f0\u7063", "utc": 1416189427000, "level": 0, "avatar": "http://filestoresg1.beetalkmobile.com:8081/file/976796239408776964", "name": "\u831c\u2764\ufe0f"}, "content": "08/17\u7345\u5b50\u5973\u5831\u5230", "urls": [], "replies": {"first": [{"content": "+1  817\u7345\u5b50", "reply": "", "id": 375691, "name": "\u827e\u8389"}], "last": [{"content": "817+", "reply": "", "id": 32213104, "name": "\u5b89\u975c\u7121\u8072"}, {"content": "+1", "reply": "", "id": 39555054, "name": "\u6953\u5c0f\u7f8a"}], "noMoreReplies": false}, "images": [], "id": 121878}, {"postBy": {"location": "\u53f0\u7063", "utc": 1416199193000, "level": 0, "avatar": "http://filestoresg1.beetalkmobile.com:8081/file/-400741198089850255", "name": "Don"}, "content": "8/2\u7345\u5b50\u7537~~~", "urls": [], "replies": {"first": [{"content": "\u548c\u6211\u540c\u3127\u5929", "reply": "", "id": 91891, "name": "\ud83d\uddff\u674e\u5c0f\u86c7\ud83c\udf34"}, {"content": "\u540c\u5929:))", "reply": "", "id": 208921, "name": "\u6d17\u8863\u7c89 :))"}], "last": [], "noMoreReplies": true}, "images": [], "id": 122789}, {"postBy": {"location": "\u5c4f\u6771\u7e23\u00b7\u53f0\u7063", "utc": 1416212252000, "level": 0, "avatar": "http://filestoresg1.beetalkmobile.com:8081/file/-5139043679372947447", "name": "\u677e\u672c \u306b\u3058"}, "content": "7/29\u7684\u7345\u5b50", "urls": [], "replies": {"first": [{"content": "+1", "reply": "", "id": 2400214, "name": "156\ud83c\udf39"}, {"content": "7/29 +1 ^^", "reply": "156\ud83c\udf39", "id": 9303708, "name": "\u300a\u599e\u300b"}], "last": [], "noMoreReplies": true}, "images": [], "id": 123992}, {"postBy": {"location": "\u5f70\u5316\u5e02\u00b7\u53f0\u7063", "utc": 1416217837000, "level": 0, "avatar": "http://filestoresg1.beetalkmobile.com:8081/file/-1197920111100286218", "name": "Yao Cheng Lai"}, "content": "7/29\u7345\u5b50", "urls": [], "replies": {"first": [], "last": [], "noMoreReplies": true}, "images": [], "id": 124527}, {"postBy": {"location": "", "utc": 1416218660000, "level": 0, "avatar": "http://filestoresg1.beetalkmobile.com:8081/file/1564088282834030464", "name": "\u4fde\u541b"}, "content": "0818\u7345\u5b50\u5973\u54e6:-)", "urls": [], "replies": {"first": [{"content": "8/18\u7345\u5b50+1", "reply": "", "id": 468014, "name": "Shiang-han Fang"}], "last": [{"content": "8/18  +1+1", "reply": "", "id": 11026272, "name": "\u8ed2"}, {"content": "8/18+1", "reply": "", "id": 55807041, "name": "\u82ae\u6db5"}], "noMoreReplies": false}, "images": [], "id": 124627}, {"postBy": {"location": "\u9e7d\u57d5\u5340\u00b7\u53f0\u7063", "utc": 1416222434000, "level": 0, "avatar": "http://filestoresg1.beetalkmobile.com:8081/file/6421345820180373023", "name": "kelly"}, "content": "8\u670810\u65e5\u7684\u7345\u5b50\u5973\u54e6\u2026", "urls": [], "replies": {"first": [{"content": "+1", "reply": "", "id": 223957, "name": "celine"}], "last": [{"content": "+1", "reply": "", "id": 8788064, "name": "\u591a\u7da0"}, {"content": "+1", "reply": "", "id": 15688603, "name": "\u6953\u82b8"}], "noMoreReplies": false}, "images": [], "id": 125029}, {"postBy": {"location": "\u65b0\u5317\u5e02,\u53f0\u7063", "utc": 1416224064000, "level": 0, "avatar": "http://filestoresg1.beetalkmobile.com:8081/file/-6651520878818574079", "name": "GoGo"}, "content": "8\uff0f9\u301c  \u55b5\uff01", "urls": [], "replies": {"first": [{"content": "me  too", "reply": "", "id": 125096, "name": "\u4e0d\u518d\u76f8\u4fe1"}], "last": [{"content": "8/9\u7345\u5b50+1><", "reply": "\u4e0d\u518d\u76f8\u4fe1", "id": 937335, "name": "\u03a3>\u2015\u7b28\u2661\u8c6c\u2014\u2192"}, {"content": "+1", "reply": "", "id": 50356227, "name": "\u554a\u878d"}], "noMoreReplies": true}, "images": [], "id": 125212}, {"postBy": {"location": "\u5c0f\u6e2f\u5340\u00b7\u53f0\u7063", "utc": 1416224361000, "level": 0, "avatar": "http://filestoresg1.beetalkmobile.com:8081/file/7649679533622402907", "name": "\u827e\u8389"}, "content": "8/17\u7345\u5b50~~~", "urls": [], "replies": {"first": [{"content": "+1", "reply": "", "id": 840365, "name": "Machine\ud83e\udd16\ud83e\udd16"}], "last": [], "noMoreReplies": true}, "images": [], "id": 125263}, {"postBy": {"location": "\u53f0\u5317\u5e02\u00b7\u53f0\u7063", "utc": 1416226662000, "level": 0, "avatar": "http://filestoresg1.beetalkmobile.com:8081/file/6114090594850060544", "name": "\u4f86\u81ea\u5916\u661f\u7684\u6211"}, "content": "727", "urls": [], "replies": {"first": [{"content": "\u54aa\u5154\uff01\u6211\u4e5f\u662f", "reply": "", "id": 880768, "name": "\u26f0Mosquito\ud83e\udd4a"}], "last": [], "noMoreReplies": true}, "images": [], "id": 125626}, {"postBy": {"location": "\u65b0\u5317\u5e02\u00b7\u53f0\u7063", "utc": 1416227363000, "level": 0, "avatar": "http://filestoresg1.beetalkmobile.com:8081/file/957451428065764253", "name": "\u5c0f\u51cc\u00ae"}, "content": "08/21\u7345\u5b50\u6b50~~", "urls": [], "replies": {"first": [{"content": "\u6211\u4e5f\u662f", "reply": "", "id": 155089, "name": "\u88dd\u4e0d\u6eff\u7684\u9152\u676f"}], "last": [{"content": "\u7d42\u65bc\u9047\u5230\u540c\u5929\u751f\u65e5\u7684\u4e86\uff5e(\u7051\u82b1", "reply": "\u88dd\u4e0d\u6eff\u7684\u9152\u676f", "id": 162334, "name": "\u5c0f\u51cc\u00ae"}, {"content": "\u52a01", "reply": "", "id": 999847, "name": "Boss Lin"}], "noMoreReplies": true}, "images": [], "id": 125736}]}
