{"noMoreComments": false, "cursorEnd": 21, "id": "893591", "comments": [{"postBy": {"location": "\u65b0\u5317\u5e02\u00b7\u53f0\u7063", "utc": 1427698939000, "level": 0, "avatar": "http://filestoresg1.beetalkmobile.com:8081/file/1704343080621310975", "name": "\u5e78\u798f\u6eff\u9ede(\uffe3\u2207\uffe3)"}, "content": "\u90fd\u597d\u770b\u2026\u2026Y(\uff3e_\uff3e)Y", "urls": [], "replies": {"first": [], "last": [], "noMoreReplies": true}, "images": [], "id": 6858247}, {"postBy": {"location": "\u9ad8\u96c4\u5e02\u00b7\u53f0\u7063", "utc": 1427699009000, "level": 0, "avatar": "http://filestoresg1.beetalkmobile.com:8081/file/-5848868595497053420", "name": "\u912d\u5bcc\u9686"}, "content": "\u90fd\u4e0d\u932f\u554a\uff5e", "urls": [], "replies": {"first": [], "last": [], "noMoreReplies": true}, "images": ["http://filestoresg1.beetalkmobile.com:8081/file/a48435103adcbfced6581924274c7f71"], "id": 6858307}, {"postBy": {"location": "\u65b0\u5317\u5e02\u00b7\u53f0\u7063", "utc": 1427701350000, "level": 0, "avatar": "http://filestoresg1.beetalkmobile.com:8081/file/-6498559014905198958", "name": "\u53e3\u963f\u53e3\u65af"}, "content": "\u597d\u96e3\u9078 135\u5de6 246\u53f3 \u79ae\u62dc\u5929\u6df7\u642d", "urls": [], "replies": {"first": [], "last": [], "noMoreReplies": true}, "images": [], "id": 6860405}, {"postBy": {"location": "\u53f0\u5317\u5e02\u00b7\u53f0\u7063", "utc": 1427701698000, "level": 0, "avatar": "http://filestoresg1.beetalkmobile.com:8081/file/-1228647061878738138", "name": "Webber Chiu"}, "content": "\u96f7\u9b3c", "urls": [], "replies": {"first": [], "last": [], "noMoreReplies": true}, "images": [], "id": 6860756}, {"postBy": {"location": "\u6843\u5712\u5e02\u00b7\u53f0\u7063", "utc": 1427702671000, "level": 0, "avatar": "http://filestoresg1.beetalkmobile.com:8081/file/1479005868184858116", "name": "181"}, "content": "\u90fd\u4e0d\u932f\u554a", "urls": [], "replies": {"first": [], "last": [], "noMoreReplies": true}, "images": [], "id": 6861693}, {"postBy": {"location": "\u6843\u5712\u5e02\u00b7\u53f0\u7063", "utc": 1427702777000, "level": 0, "avatar": "http://filestoresg1.beetalkmobile.com:8081/file/-8990270072595769568", "name": "\u767d"}, "content": "\u96d9\u99ac\u5c3e\u6700\u9ad8!!!", "urls": [], "replies": {"first": [], "last": [], "noMoreReplies": true}, "images": [], "id": 6861812}, {"postBy": {"location": "\u6843\u5712\u5e02\u00b7\u53f0\u7063", "utc": 1427702807000, "level": 0, "avatar": "http://filestoresg1.beetalkmobile.com:8081/file/-2644730083084784159", "name": "\u963f\u6b23"}, "content": "\u4e2d\u5206\u77ed\u9aee\uff01\u65c1\u5206\u77ed\u9aee\uff01\u611f\u89ba\u59b3\u77ed\u9aee\u6bd4\u8f03\u597d\u770b\u3002", "urls": [], "replies": {"first": [], "last": [], "noMoreReplies": true}, "images": [], "id": 6861841}, {"postBy": {"location": "\u53f0\u5357\u5e02\u00b7\u53f0\u7063", "utc": 1427703442000, "level": 0, "avatar": "http://filestoresg1.beetalkmobile.com:8081/file/-691463070245850365", "name": "\u795e\u5a01\u986f\u8d6b"}, "content": "\u7b2c\u4e8c", "urls": [], "replies": {"first": [], "last": [], "noMoreReplies": true}, "images": [], "id": 6862468}, {"postBy": {"location": "\u65b0\u5317\u5e02\u00b7\u53f0\u7063", "utc": 1427703471000, "level": 0, "avatar": "http://filestoresg1.beetalkmobile.com:8081/file/-259022948065546239", "name": "\u53ef\u60e1\ud83d\ude08"}, "content": "\u4e2d\u5206\u597d\u770b\u6b38", "urls": [], "replies": {"first": [], "last": [], "noMoreReplies": true}, "images": [], "id": 6862492}, {"postBy": {"location": "\u9ad8\u96c4\u5e02\u00b7\u53f0\u7063", "utc": 1427703545000, "level": 0, "avatar": "http://filestoresg1.beetalkmobile.com:8081/file/-8195814647920940938", "name": "Roger"}, "content": "\u611f\u89ba\u59b3\u4e2d\u5206\u6703\u7a7a\u6c23\u61c9\u8a72\u90fd\u4e0d\u932f", "urls": [], "replies": {"first": [], "last": [], "noMoreReplies": true}, "images": [], "id": 6862560}, {"postBy": {"location": "\u65b0\u7af9\u5e02\u00b7\u53f0\u7063", "utc": 1427704685000, "level": 0, "avatar": "http://filestoresg1.beetalkmobile.com:8081/file/7564974259637673998", "name": "\u6211\u6234\u8457\u5feb\u6a02\u7684\u9762\u5177"}, "content": "\u7d81\u500b\u96d9\u8fae\u5b50\u5982\u4f55", "urls": [], "replies": {"first": [], "last": [], "noMoreReplies": true}, "images": [], "id": 6863583}, {"postBy": {"location": "\u6843\u5712\u5e02\u00b7\u53f0\u7063", "utc": 1427707183000, "level": 0, "avatar": "http://filestoresg1.beetalkmobile.com:8081/file/-6959817340452350143", "name": "\u96e8\u5929\u6674"}, "content": "\u55ae\u99ac\u5c3e\u597d\u4e86\uff01", "urls": [], "replies": {"first": [], "last": [], "noMoreReplies": true}, "images": [], "id": 6865736}, {"postBy": {"location": "\u57fa\u9686\u5e02\u00b7\u53f0\u7063", "utc": 1427709310000, "level": 0, "avatar": "http://filestoresg1.beetalkmobile.com:8081/file/-9015951357853199584", "name": "\u8c6a\u4ed4"}, "content": "\u4e2d\u5206\u2026\u5427", "urls": [], "replies": {"first": [], "last": [], "noMoreReplies": true}, "images": [], "id": 6867550}, {"postBy": {"location": "\u53f0\u4e2d\u5e02\u00b7\u53f0\u7063", "utc": 1427723034000, "level": 0, "avatar": "http://filestoresg1.beetalkmobile.com:8081/file/3218961035747358651", "name": "\u5241\u982d\u9aee"}, "content": "\u7b2c\u4e00", "urls": [], "replies": {"first": [], "last": [], "noMoreReplies": true}, "images": [], "id": 6882125}, {"postBy": {"location": "\u82b1\u84ee\u7e23\u00b7\u53f0\u7063", "utc": 1427746854000, "level": 0, "avatar": "http://filestoresg1.beetalkmobile.com:8081/file/7928149539814320773", "name": "Y"}, "content": "\u5149\u982d", "urls": [], "replies": {"first": [], "last": [], "noMoreReplies": true}, "images": [], "id": 6905894}, {"postBy": {"location": "\u6843\u5712\u5e02\u00b7\u53f0\u7063", "utc": 1427749707000, "level": 0, "avatar": "http://filestoresg1.beetalkmobile.com:8081/file/-8787830188023170113", "name": "^Big Hong^"}, "content": "\u77ed\u9aee", "urls": [], "replies": {"first": [], "last": [], "noMoreReplies": true}, "images": [], "id": 6906673}, {"postBy": {"location": "\u6843\u5712\u5e02\u00b7\u53f0\u7063", "utc": 1427750344000, "level": 0, "avatar": "http://filestoresg1.beetalkmobile.com:8081/file/1002522610204678278", "name": "\u7dad\u7dad"}, "content": "\u53f3\u5716", "urls": [], "replies": {"first": [], "last": [], "noMoreReplies": true}, "images": [], "id": 6906838}, {"postBy": {"location": "\u5357\u6295\u7e23\u00b7\u53f0\u7063", "utc": 1427750910000, "level": 0, "avatar": "http://filestoresg1.beetalkmobile.com:8081/file/3567117259029390706", "name": "\u7121\u5948"}, "content": "\u6293\u982d\u9aee\u90a3\u5f35", "urls": [], "replies": {"first": [], "last": [], "noMoreReplies": true}, "images": [], "id": 6906949}, {"postBy": {"location": "\u53f0\u5317\u5e02\u00b7\u53f0\u7063", "utc": 1427752151000, "level": 0, "avatar": "http://filestoresg1.beetalkmobile.com:8081/file/-5561047611406802687", "name": "Gary"}, "content": "\u65c1\u5206", "urls": [], "replies": {"first": [], "last": [], "noMoreReplies": true}, "images": [], "id": 6907255}]}
