{"noMoreComments": false, "cursorEnd": 22, "id": "447416", "comments": [{"postBy": {"location": "\u53f0\u4e2d\u5e02\u00b7\u53f0\u7063", "utc": 1423372290000, "level": 0, "avatar": "http://filestoresg1.beetalkmobile.com:8081/file/7330431932665177640", "name": "\u8eca\u7ad9\u7559\u8a00\u677f\u7684XYZ"}, "content": "\u597d\u7d30\u7dfb!", "urls": [], "replies": {"first": [{"content": "\u6211\u559c\u6b61\u985e\u4f3c\u5de5\u7b46\u756b\u7684\u611f\u89ba\u2665", "reply": "", "id": 2272443, "name": "\u5c11\u5973\u5fc3\u963f\u59e8Pinky\ud83d\ude17"}], "last": [{"content": "\u02ca\u02c7\u02cb \u8981\u5f88\u6709\u8010\u5fc3", "reply": "\u5c11\u5973\u5fc3\u963f\u59e8Pinky\ud83d\ude17", "id": 2286979, "name": "\u8eca\u7ad9\u7559\u8a00\u677f\u7684XYZ"}, {"content": "\u6211\u4e5f\u5f88\u559c\u6b61\u5de5\u7b46\u756b\u2026", "reply": "\u5c11\u5973\u5fc3\u963f\u59e8Pinky\ud83d\ude17", "id": 3391934, "name": "\u273f\u5982\u973d\u273f"}], "noMoreReplies": true}, "images": [], "id": 3160568}, {"postBy": {"location": "\u53f0\u5317\u5e02\u00b7\u53f0\u7063", "utc": 1423374105000, "level": 0, "avatar": "http://filestoresg1.beetalkmobile.com:8081/file/1628919882465790404", "name": "Tony0720"}, "content": "\u53b2\u5bb3", "urls": [], "replies": {"first": [{"content": "\u8b1d\u8b1d///\u4f60\u62cd\u7684\u7167\u7247\u4e5f\u5f88\u597d\u770b\uff01", "reply": "", "id": 2272414, "name": "\u5c11\u5973\u5fc3\u963f\u59e8Pinky\ud83d\ude17"}], "last": [], "noMoreReplies": true}, "images": [], "id": 3161857}, {"postBy": {"location": "\u65b0\u5317\u5e02\u00b7\u53f0\u7063", "utc": 1423375162000, "level": 0, "avatar": "http://filestoresg1.beetalkmobile.com:8081/file/-3290106020158245872", "name": "\u6d6a\u82b1\u5409\u666e\u8cfd"}, "content": "\u597d\u5f37\u3002\u3002\u3002\u3002\u3002\u3002\u8acb\u53d7\u68a8\u5b50\u4e00\u62dc~", "urls": [], "replies": {"first": [{"content": "\u8b1d\u8b1d\u559c\u6b61~~~><", "reply": "", "id": 2272339, "name": "\u5c11\u5973\u5fc3\u963f\u59e8Pinky\ud83d\ude17"}, {"content": "\u771f\u7684\u5f88\u53b2\u5bb3~", "reply": "", "id": 2283472, "name": "\u6d6a\u82b1\u5409\u666e\u8cfd"}], "last": [], "noMoreReplies": true}, "images": [], "id": 3162574}, {"postBy": {"location": "\u5317\u5c6f\u5340\u00b7\u53f0\u7063", "utc": 1423376161000, "level": 0, "avatar": "http://filestoresg1.beetalkmobile.com:8081/file/-2996806901053316358", "name": "seagull"}, "content": "\u597d\u53b2\u5bb3\u54e6  \u559c\u6b61\u4f60\u9019\u7a2e\u7570\u60f3\u4e16\u754c\u7684\u98a8\u683c", "urls": [], "replies": {"first": [{"content": "\u8b1d\u8b1d\u559c\u6b61///", "reply": "", "id": 2272213, "name": "\u5c11\u5973\u5fc3\u963f\u59e8Pinky\ud83d\ude17"}], "last": [], "noMoreReplies": true}, "images": [], "id": 3163240}, {"postBy": {"location": "\u5f70\u5316\u7e23\u00b7\u53f0\u7063", "utc": 1423378655000, "level": 0, "avatar": "http://filestoresg1.beetalkmobile.com:8081/file/-2681821008145735936", "name": "EJ"}, "content": "\u6709\u7a2e\u6155\u590f\u7684\u611f\u89ba", "urls": [], "replies": {"first": [], "last": [], "noMoreReplies": true}, "images": [], "id": 3165025}, {"postBy": {"location": "\u9ad8\u96c4\u5e02\u00b7\u53f0\u7063", "utc": 1423380711000, "level": 0, "avatar": "http://filestoresg1.beetalkmobile.com:8081/file/-538714514235265643", "name": "\u6e38\u8463"}, "content": "\u597d\u770b\uff5e\u597d\u6703\u756b", "urls": [], "replies": {"first": [], "last": [], "noMoreReplies": true}, "images": [], "id": 3166482}, {"postBy": {"location": "\u5f70\u5316\u7e23\u00b7\u53f0\u7063", "utc": 1423396984000, "level": 0, "avatar": "http://filestoresg1.beetalkmobile.com:8081/file/1758584188550162960", "name": "Qqabcdefg"}, "content": "\u8acb\u554f\u984f\u8272\u4e5f\u662f\u539f\u5b50\u7b46\u9084\u662f\u96fb\u8166", "urls": [], "replies": {"first": [], "last": [], "noMoreReplies": true}, "images": [], "id": 3177416}, {"postBy": {"location": "\u65b0\u5317\u5e02\u00b7\u53f0\u7063", "utc": 1423404544000, "level": 0, "avatar": "http://filestoresg1.beetalkmobile.com:8081/file/-4854686878926613230", "name": "YEN"}, "content": "\u69cb\u5716\u5f88\u5f37\u8036\uff01\uff01", "urls": [], "replies": {"first": [], "last": [], "noMoreReplies": true}, "images": [], "id": 3183649}, {"postBy": {"location": "\u82d7\u6817\u7e23\u00b7\u53f0\u7063", "utc": 1423407158000, "level": 0, "avatar": "http://filestoresg1.beetalkmobile.com:8081/file/-4776253218073702363", "name": "\u264e"}, "content": "So cool!!!", "urls": [], "replies": {"first": [], "last": [], "noMoreReplies": true}, "images": [], "id": 3186124}, {"postBy": {"location": "\u53f0\u4e2d\u5e02\u00b7\u53f0\u7063", "utc": 1423411435000, "level": 0, "avatar": "http://filestoresg1.beetalkmobile.com:8081/file/3509873120245555944", "name": "\u6e5b\u85cd"}, "content": "\u5df2\u8dea", "urls": [], "replies": {"first": [], "last": [], "noMoreReplies": true}, "images": [], "id": 3190466}, {"postBy": {"location": "\u57fa\u9686\u5e02\u00b7\u53f0\u7063", "utc": 1423414112000, "level": 0, "avatar": "http://filestoresg1.beetalkmobile.com:8081/file/-5425271846423494553", "name": "DNight"}, "content": "\u597d\u53b2\u5bb3\uff01\uff01", "urls": [], "replies": {"first": [], "last": [], "noMoreReplies": true}, "images": [], "id": 3193114}, {"postBy": {"location": "\u53f0\u5317\u5e02\u00b7\u53f0\u7063", "utc": 1423415781000, "level": 0, "avatar": "http://filestoresg1.beetalkmobile.com:8081/file/1183395573788970392", "name": "\u6b4c\u7483"}, "content": "\u54c7\u54e9\u52d2@@\uff01\uff01\uff01\uff01\uff01<br />\u9047\u5230\u795e\u4eba\uff01\uff01\uff01<br />\u53d7\u5c0f\u4eba\u4e00\u62dc\u554a\uff01\uff01", "urls": [], "replies": {"first": [], "last": [], "noMoreReplies": true}, "images": [], "id": 3194447}, {"postBy": {"location": "", "utc": 1423419215000, "level": 0, "avatar": "http://filestoresg1.beetalkmobile.com:8081/file/5425636885787209098", "name": "\u270c\u5154\u723a"}, "content": "\u4f60\u4f60\u4f60\u4f60\u2026\u2026\u9019\u9019\u9019\u9019\u2026\u2026<br />\u592a\u53b2\u5bb3\u4e86 \u6211\u2026\u6211\u7d50\u5df4\u4e860.0", "urls": [], "replies": {"first": [], "last": [], "noMoreReplies": true}, "images": [], "id": 3196638}, {"postBy": {"location": "", "utc": 1423446582000, "level": 0, "avatar": "http://filestoresg1.beetalkmobile.com:8081/file/-2167190186267197077", "name": "light"}, "content": "\u5f88\u8b9a\u8036", "urls": [], "replies": {"first": [], "last": [], "noMoreReplies": true}, "images": [], "id": 3205981}, {"postBy": {"location": "", "utc": 1423448072000, "level": 0, "avatar": "http://filestoresg1.beetalkmobile.com:8081/file/-5739137327545732487", "name": "\u7def\u7def"}, "content": "\u597d\u53b2\u5bb3\u5594\uff01\u771f\u68d2\u5462\uff01", "urls": [], "replies": {"first": [], "last": [], "noMoreReplies": true}, "images": [], "id": 3206784}, {"postBy": {"location": "\u65b0\u5317\u5e02\u00b7\u53f0\u7063", "utc": 1423450807000, "level": 0, "avatar": "http://filestoresg1.beetalkmobile.com:8081/file/-5969493574170372348", "name": "\u8001\u7070\u4ed4"}, "content": "\u597d\u53b2\u5bb3\uff01\u795e\u4eba\u22ef", "urls": [], "replies": {"first": [], "last": [], "noMoreReplies": true}, "images": [], "id": 3208520}, {"postBy": {"location": "\u53f0\u5357\u5e02\u00b7\u53f0\u7063", "utc": 1423452759000, "level": 0, "avatar": "http://filestoresg1.beetalkmobile.com:8081/file/-6267569219679773675", "name": "\u9dc9\u9e06"}, "content": "\u4f60\u756b\u7684\u597d\u7f8e<br />\u6211\u9802\u591a\u756ba4 \u7684 \u5c31\u89ba\u5f97\u5f88\u7d2f\u4e86", "urls": [], "replies": {"first": [], "last": [], "noMoreReplies": true}, "images": ["http://filestoresg1.beetalkmobile.com:8081/file/ed695d93e0608dd55a8ab397fffb2617"], "id": 3209827}, {"postBy": {"location": "\u65b0\u5317\u5e02\u00b7\u53f0\u7063", "utc": 1423453279000, "level": 0, "avatar": "http://filestoresg1.beetalkmobile.com:8081/file/-8635943653058038212", "name": "\u96e8\u970f\ud83d\udc2c"}, "content": "\u597d\u53b2\u5bb3\u2661\u771f\u6709\u624d\u83ef", "urls": [], "replies": {"first": [], "last": [], "noMoreReplies": true}, "images": [], "id": 3210158}, {"postBy": {"location": "\u65b0\u5317\u5e02\u00b7\u53f0\u7063", "utc": 1423455787000, "level": 0, "avatar": "http://filestoresg1.beetalkmobile.com:8081/file/1429422296601694057", "name": "\u602a\u982d"}, "content": "\u7dda\u689d\u80fd\u529b\u5f88\u5f37\u7684\u9ad8\u624b\u5594\uff01", "urls": [], "replies": {"first": [], "last": [], "noMoreReplies": true}, "images": [], "id": 3211896}]}
