{"noMoreComments": true, "cursorEnd": 0, "id": "3403", "comments": [{"postBy": {"location": "", "utc": 1415163882000, "level": 0, "avatar": "http://filestoresg1.beetalkmobile.com:8081/file/42849074355977623", "name": "\u591c\u9b45\u7d2b\u6708"}, "content": "\u6211\u7684\u4e8c\u6b21\u5143\u7537\u795eXD", "urls": [], "replies": {"first": [], "last": [], "noMoreReplies": true}, "images": ["http://filestoresg1.beetalkmobile.com:8081/file/055f1b32e0e305b39259f943f65879cf", "http://filestoresg1.beetalkmobile.com:8081/file/e06389fc01605ee0688bbbfe12ac0806", "http://filestoresg1.beetalkmobile.com:8081/file/4345e52b02d5ba7241da8f6d06f87217", "http://filestoresg1.beetalkmobile.com:8081/file/70a8d4fdeb772f89ff1bfe557c6a3c14", "http://filestoresg1.beetalkmobile.com:8081/file/be0b14cc7f56b42aac92632084527195"], "id": 36868}, {"postBy": {"location": "\u5c0f\u6e2f\u5340\u00b7\u53f0\u7063", "utc": 1415184914000, "level": 0, "avatar": "http://filestoresg1.beetalkmobile.com:8081/file/748425476731246476", "name": "\u590f\u591c"}, "content": "\u72ac\u591c\u53c9\u554a~~~~~<<\u9019\u4eba\u8d85\u611b\u7684", "urls": [], "replies": {"first": [], "last": [], "noMoreReplies": true}, "images": [], "id": 37988}, {"postBy": {"location": "\u592a\u5e73\u5340\u00b7\u53f0\u7063", "utc": 1415211179000, "level": 0, "avatar": "http://filestoresg1.beetalkmobile.com:8081/file/7512107533701615901", "name": "yinnnn\ud83d\udc95"}, "content": "\u9059~~~", "urls": [], "replies": {"first": [], "last": [], "noMoreReplies": true}, "images": ["http://filestoresg1.beetalkmobile.com:8081/file/c668d1a3c142e91ba905c47ea2e65111"], "id": 40435}, {"postBy": {"location": "\u5b89\u5e73\u5340\u00b7\u53f0\u7063", "utc": 1415378881000, "level": 0, "avatar": "http://filestoresg1.beetalkmobile.com:8081/file/5987754509385833582", "name": "Love?\u5e7d\u5e7d"}, "content": "\u6211\u7684\u4e8c\u6b21\u5143\u7537\u795e~~", "urls": [], "replies": {"first": [], "last": [], "noMoreReplies": true}, "images": ["http://filestoresg1.beetalkmobile.com:8081/file/ef440caf25a206a9c120752a897ba33f", "http://filestoresg1.beetalkmobile.com:8081/file/f5aeb0e2288c733dd44beeefe561d06a", "http://filestoresg1.beetalkmobile.com:8081/file/1397732b143a17d528dcbe653c546bcf", "http://filestoresg1.beetalkmobile.com:8081/file/56380899933add4d39f802a384c5b2ec", "http://filestoresg1.beetalkmobile.com:8081/file/648f1c6c9dfad4543ddf5cf830ae74b1", "http://filestoresg1.beetalkmobile.com:8081/file/7e264459e49beab5da81e1cfa56e2671"], "id": 50959}, {"postBy": {"location": "\u5b89\u5e73\u5340\u00b7\u53f0\u7063", "utc": 1415379149000, "level": 0, "avatar": "http://filestoresg1.beetalkmobile.com:8081/file/5987754509385833582", "name": "Love?\u5e7d\u5e7d"}, "content": "\u9084\u6709", "urls": [], "replies": {"first": [], "last": [], "noMoreReplies": true}, "images": ["http://filestoresg1.beetalkmobile.com:8081/file/e2cc003e25626d8cd9513811fcf19382", "http://filestoresg1.beetalkmobile.com:8081/file/5acc0e6d0e435fff9fc426d27eaf832b", "http://filestoresg1.beetalkmobile.com:8081/file/1c878d8e2340d915efcdfb006603c0de", "http://filestoresg1.beetalkmobile.com:8081/file/1fccc356596f7afc59b0b05ea948c4a6", "http://filestoresg1.beetalkmobile.com:8081/file/f564e09f644b5c827f0fbf989f3b498d", "http://filestoresg1.beetalkmobile.com:8081/file/a0133a6d12648d914d42668ba584f822"], "id": 50986}, {"postBy": {"location": "\u592a\u5e73\u5340\u00b7\u53f0\u7063", "utc": 1415382732000, "level": 0, "avatar": "http://filestoresg1.beetalkmobile.com:8081/file/-6776501265497748135", "name": "\u8c93\u5b43"}, "content": "\u6211\u7684\u4e8c\u6b21\u5143\u7537\u795e", "urls": [], "replies": {"first": [], "last": [], "noMoreReplies": true}, "images": ["http://filestoresg1.beetalkmobile.com:8081/file/ba8a14364cd893f75ced400f599ab909"], "id": 51354}, {"postBy": {"location": "\u745e\u82b3\u5340\u00b7\u53f0\u7063", "utc": 1415470742000, "level": 0, "avatar": "http://filestoresg1.beetalkmobile.com:8081/file/2488182719865815954", "name": "\u8863\u8896"}, "content": "\u99ac\u6751\u548c\u8001\u5e2b\u311a\u311a", "urls": [], "replies": {"first": [{"content": "\u6211\u611b\u99ac\u6751\uff01\uff01\uff01\uff01\uff01\uff01\uff01", "reply": "", "id": 33690, "name": "\u963f\u5c1a"}], "last": [], "noMoreReplies": true}, "images": ["http://filestoresg1.beetalkmobile.com:8081/file/a55c3e18f8dd0723971c5c22e2d343a4"], "id": 57655}, {"postBy": {"location": "\u6587\u5c71\u5340\u00b7\u53f0\u7063", "utc": 1415751815000, "level": 0, "avatar": "http://filestoresg1.beetalkmobile.com:8081/file/1", "name": "\u590f\u7384\u5141"}, "content": "\u5e25\u554a", "urls": [], "replies": {"first": [], "last": [], "noMoreReplies": true}, "images": ["http://filestoresg1.beetalkmobile.com:8081/file/46aa1fa0dda9e478b9e27149a0370d26", "http://filestoresg1.beetalkmobile.com:8081/file/b0b18ceec7b5bab0eba1454abb617e44", "http://filestoresg1.beetalkmobile.com:8081/file/5bcad5cb2cfc651d406ccda7a6f2dfd3", "http://filestoresg1.beetalkmobile.com:8081/file/6ea50ce1152b12a1bb376d4e2442fffc", "http://filestoresg1.beetalkmobile.com:8081/file/0facfcbf46b4cae8d4334f0a2f04d85a", "http://filestoresg1.beetalkmobile.com:8081/file/9c0363c2afd175cd4632018916127231"], "id": 80968}]}
