{"noMoreComments": false, "cursorEnd": 22, "id": "674296", "comments": [{"postBy": {"location": "\u6843\u5712\u5e02\u00b7\u53f0\u7063", "utc": 1425560925000, "level": 0, "avatar": "http://filestoresg1.beetalkmobile.com:8081/file/6336097390669093164", "name": "\u9b6f\u554a\u9b6f"}, "content": "\u6211\u6709\u770b\u52d5\u6f2b\uff0c\u7537\u4e3b\u89d2\u883b\u5f37\u7684", "urls": [], "replies": {"first": [{"content": "\u722c\u5761\u5929\u624d~", "reply": "", "id": 3524010, "name": "\u7d2b\u539f"}], "last": [{"content": "\u4e0d\u662f\u5929\u624d\u55b2\u2026\u2026\u2026\n\u4f5c\u8005\u6f2b\u756b\u6709\u984c\u5230 \u4ee5\u524d\u4f4f\u5728\u6df1\u5c71\u5167\u70ba\u4e86\u9577\u9014\u8dcb\u6d89\u53bb\u79cb\u8449\u539f \u6240\u4ee5 \u7121\u610f\u9593 \u935b\u934a\u7684\u8173", "reply": "\u7d2b\u539f", "id": 4160025, "name": "\u53c8\u5b85\u53c8\u521d\u3010 \u264d \u3011"}, {"content": "\u800c\u4e14\u5abd\u5abd\u9084\u628a\u6b64\u8f2a\u5077\u5077\u63db\u5c0f\u4e00\u9ede", "reply": "", "id": 4164815, "name": "\u9b6f\u554a\u9b6f"}], "noMoreReplies": false}, "images": [], "id": 5036321}, {"postBy": {"location": "\u82d7\u6817\u7e23\u00b7\u53f0\u7063", "utc": 1425676891000, "level": 0, "avatar": "http://filestoresg1.beetalkmobile.com:8081/file/6190843105742426025", "name": "\ud83d\ude0a "}, "content": "\u4e4b\u524d\u96fb\u8996\u6709\u64ad\u6211\u6709\u770b<br />\u89ba\u5f97\u6eff\u597d\u770b\u7684\u4e5f\u5f88\u71b1\u8840 \ud83d\ude0a \ud83d\udc4d", "urls": [], "replies": {"first": [{"content": "\u771f\u7684\u6eff\u71b1\u8840", "reply": "", "id": 3658150, "name": "\u7d2b\u539f"}], "last": [{"content": "\u53ef\u4ee5\u770b\u83ef\u8996\u9031\u516d~\u516d\u9ede\u6709\u64ad", "reply": "\ud83d\ude0a ", "id": 3694257, "name": "\u7d2b\u539f"}, {"content": "OK \ud83d\ude0a", "reply": "\u7d2b\u539f", "id": 3699499, "name": "\ud83d\ude0a "}], "noMoreReplies": false}, "images": [], "id": 5149049}, {"postBy": {"location": "\u65b0\u5317\u5e02\u00b7\u53f0\u7063", "utc": 1425685580000, "level": 0, "avatar": "http://filestoresg1.beetalkmobile.com:8081/file/-7080383183909398683", "name": "a"}, "content": "\u5f88\u71b1\u8840\ud83d\ude01", "urls": [], "replies": {"first": [], "last": [], "noMoreReplies": true}, "images": [], "id": 5152760}, {"postBy": {"location": "\u57fa\u9686\u5e02\u00b7\u53f0\u7063", "utc": 1425761847000, "level": 0, "avatar": "http://filestoresg1.beetalkmobile.com:8081/file/8769101112917436545", "name": "\u98df\u8089\u52d5\u7269"}, "content": "\u6211\u56e0\u70ba\u770b\u9019\u90e8\u52d5\u756b\u611b\u4e0a\u55ae\u8eca\u7684!:)", "urls": [], "replies": {"first": [{"content": "\u8b9a~", "reply": "", "id": 3658429, "name": "\u7d2b\u539f"}], "last": [{"content": "\u9127\u8eca\u662f\u4ec0\u9ebc\u5566!! \u4e0d\u904e\u4e4b\u524d\u6709\u5b78\u5fa1\u5802\u7b4b\u7684\u65b9\u5f0f\u9a0e\u8eca\u5dee\u9ede\u6454\u8eca.......", "reply": "", "id": 4160606, "name": "\u98df\u8089\u52d5\u7269"}, {"content": "\u9084\u662f\u5b78\u6771\u5802\u5427\u6c88\u7761\u722c\u5761~\u4e0d\u7136\u5377\u5cf6\u4e5f\u4e0d\u932f\u4e0d\u904e\u61c9\u8a72\u6703\u88ab\u7576\u760b\u5b50", "reply": "\u98df\u8089\u52d5\u7269", "id": 5292751, "name": "\u7d2b\u539f"}], "noMoreReplies": false}, "images": ["http://filestoresg1.beetalkmobile.com:8081/file/edbc45dd7161c4483c8ca2db97cb7c51", "http://filestoresg1.beetalkmobile.com:8081/file/1323b7e3baf25ffd1521ed9914d593e1", "http://filestoresg1.beetalkmobile.com:8081/file/f9284932fd3bbe2019ef56adbffb54e9", "http://filestoresg1.beetalkmobile.com:8081/file/0727eb953c380c7bd2adcb7d0b99eccb", "http://filestoresg1.beetalkmobile.com:8081/file/41b50236f924bf69b815f2246b48455c", "http://filestoresg1.beetalkmobile.com:8081/file/be6c4d6ca67314aa9fb562a80d5d0d87"], "id": 5232320}, {"postBy": {"location": "\u6843\u5712\u5e02\u00b7\u53f0\u7063", "utc": 1425779791000, "level": 0, "avatar": "http://filestoresg1.beetalkmobile.com:8081/file/-6301264853479661370", "name": "\u522a\u4e86"}, "content": "\u4eca\u6cc9\u5927\u611b\u2661\u2661\u2661", "urls": [], "replies": {"first": [{"content": "\u54c8~\u6211\u662f\u7bb1\u6839\u6d3e\u7684~\u65b0\u958b\u6e96\u4eba", "reply": "", "id": 3662517, "name": "\u7d2b\u539f"}], "last": [], "noMoreReplies": true}, "images": [], "id": 5241949}, {"postBy": {"location": "\u65b0\u5317\u5e02\u00b7\u53f0\u7063", "utc": 1426032184000, "level": 0, "avatar": "http://filestoresg1.beetalkmobile.com:8081/file/8446658332640102673", "name": "REX \u264e\ufe0f \u7f8a\u4ed4\u5152"}, "content": "\u5c0f\u884c\u5b57\u5e55\u7b2c\u4e8c\u5b63\u5c31GG\u505c\u756a", "urls": [], "replies": {"first": [], "last": [], "noMoreReplies": true}, "images": [], "id": 5466234}, {"postBy": {"location": "Hsinchu County\u00b7Taiwan", "utc": 1426070190000, "level": 0, "avatar": "http://filestoresg1.beetalkmobile.com:8081/file/5217573003126493307", "name": "\u5446\u90c1\u062a"}, "content": "\u8d85\u611b~~", "urls": [], "replies": {"first": [{"content": "\u54c8~me too", "reply": "", "id": 3857758, "name": "\u7d2b\u539f"}, {"content": "\u8d85\u95dc\u6ce8", "reply": "", "id": 3901101, "name": "\u5446\u90c1\u062a"}], "last": [], "noMoreReplies": true}, "images": [], "id": 5498306}, {"postBy": {"location": "\u53f0\u5317\u5e02\u00b7\u53f0\u7063", "utc": 1426071546000, "level": 0, "avatar": "http://filestoresg1.beetalkmobile.com:8081/file/112698845555911901", "name": "\u85cd\u3105"}, "content": " \u6211\u524d\u5e7e\u5929\u624d\u62cd\u5b8c\u5496\u5561\u5ef3\u7248\u672c\u7684\u5c71\u5742^^^", "urls": [], "replies": {"first": [{"content": "\u5c71\u5742\u662f...\u6211\u770b\u5230\u7d2b\u539f\u6566cos~~\u54c7", "reply": "", "id": 3857872, "name": "\u7d2b\u539f"}], "last": [{"content": "\u5c71\u5cb3x\u5742\u9053._.", "reply": "\u7d2b\u539f", "id": 3893088, "name": "\u85cd\u3105"}, {"content": "=\u53e3=\u539f\u4f86\u662f\u9019\u6a23~", "reply": "\u85cd\u3105", "id": 3898051, "name": "\u7d2b\u539f"}], "noMoreReplies": true}, "images": [], "id": 5499576}, {"postBy": {"location": "\u6843\u5712\u5e02\u00b7\u53f0\u7063", "utc": 1426073226000, "level": 0, "avatar": "http://filestoresg1.beetalkmobile.com:8081/file/3024509102074682382", "name": "Ray"}, "content": "\u524d\u9762\u6eff\u597d\u770b\u7684\uff0c\u5f88\u71b1\u8840\uff01<br />\u5f8c\u9762\u5c31\u662f\u8ab0\u543c\u7684\u5927\u8072\u8ab0\u5c31\u8d0f...<br />\u91cd\u9ede\u662f\u8ddd\u96e2\u548c\u52d5\u756b\u5448\u73fe\u7684\u901f\u5ea6\u611f\u7121\u6cd5\u5c0d\u4e0a", "urls": [], "replies": {"first": [], "last": [], "noMoreReplies": true}, "images": [], "id": 5501267}, {"postBy": {"location": "\u65b0\u5317\u5e02\u00b7\u53f0\u7063", "utc": 1426148620000, "level": 0, "avatar": "http://filestoresg1.beetalkmobile.com:8081/file/4279165124311130016", "name": "\u9670\u5ddd\u30ad\u30c4\u30cd"}, "content": "\u6f2b\u756b\u6bcf\u96c6\u90fd\u6709\u597d\u597d\u7684\u8ffd\ud83d\ude09<br />\u6700\u559c\u6b61\u722c\u5761\u7d44\u8ddf\u5354\u8abf\u7d44<br />\u65b0\u7bb1\u6839\u4e5f\u5f88\u559c\u6b61\u53ef\u662f\u6bd4\u8d77\u4f86\u679c\u7136\u9084\u662f\u559c\u6b61\u7e3d\u5317\u5440\uff01(\u56e0\u70ba\u6700\u559c\u6b61\u5742\u9053\u4e86)<br />\u9084\u6709\u6211\u89ba\u5f97\uff0c\u5982\u679c\u6771\u5802\u662f\u7bb1\u6839\u6700\u7f8e\u578b\uff0c\u90a3\u65b0\u958b\u5c31\u662f\u7bb1\u6839\u6700\u5e25-///-", "urls": [], "replies": {"first": [{"content": "\u771f\u7684\u7bb1\u6839\u76f4\u7dda\u9b3c\u6700\u5e25\u4e86", "reply": "", "id": 3898094, "name": "\u7d2b\u539f"}], "last": [], "noMoreReplies": true}, "images": [], "id": 5562321}, {"postBy": {"location": "\u6843\u5712\u5e02\u00b7\u53f0\u7063", "utc": 1426211808000, "level": 0, "avatar": "http://filestoresg1.beetalkmobile.com:8081/file/811054760771708548", "name": "\u96e8\u6b23\ud83c\udf80"}, "content": "\u516c\u4e3b\u516c\u4e3b\u02d9\u02d9<br />\u559c\u6b61\u559c\u6b61\u8d85\u559c\u6b61~", "urls": [], "replies": {"first": [{"content": "\u54c8~", "reply": "", "id": 3957453, "name": "\u7d2b\u539f"}, {"content": "\u51b0\u6cc9\u771f\u7684\u5f88\u5e25\u5462\u02ca\u02c7\u02cb", "reply": "\u7d2b\u539f", "id": 3972053, "name": "\u96e8\u6b23\ud83c\udf80"}], "last": [], "noMoreReplies": true}, "images": [], "id": 5610546}, {"postBy": {"location": "\u53f0\u5317\u5e02\u00b7\u53f0\u7063", "utc": 1426255314000, "level": 0, "avatar": "http://filestoresg1.beetalkmobile.com:8081/file/3695295857408233692", "name": "\u4f50\u91ce\u6b63\u5fd7"}, "content": "\u9084\u6eff\u71b1\u8840\u7684   \u9019\u5b63\u5feb\u7d50\u675f\u4e86", "urls": [], "replies": {"first": [], "last": [], "noMoreReplies": true}, "images": [], "id": 5647571}, {"postBy": {"location": "", "utc": 1426318593000, "level": 0, "avatar": "http://filestoresg1.beetalkmobile.com:8081/file/-1534824770244884981", "name": "Jk"}, "content": "\u6211\u6709\u770b\uff0c\u6eff\u71b1\u8840\u7684", "urls": [], "replies": {"first": [], "last": [], "noMoreReplies": true}, "images": [], "id": 5695803}, {"postBy": {"location": "\u53f0\u5357\u5e02\u00b7\u53f0\u7063", "utc": 1426375201000, "level": 0, "avatar": "http://filestoresg1.beetalkmobile.com:8081/file/-3000662887792545435", "name": "\u8c93\u718a\u809a\u5b50\u975e\u5e38\u5927"}, "content": "\u5f88\u597d\u770b\u4f46\u662f\u597d\u62d6\u6232\uff01\u800c\u4e14\u5287\u60c5\u5206\u679d\u958b\u592a\u591a\uff01\u4e0d\u662f\u4e3b\u89d2\u5b78\u6821\u7684\u4e5f\u5f88\u591a\u5c0f\u6545\u4e8b\uff0c\u61c9\u8a72\u53e6\u958b\u756a\u5916\u7bc7\u4ecb\u7d39\u5c31\u597d\uff0c\u592a\u62d6\u6232\u4e86\u5566\uff01", "urls": [], "replies": {"first": [], "last": [], "noMoreReplies": true}, "images": [], "id": 5741134}, {"postBy": {"location": "\u82d7\u6817\u7e23\u00b7\u53f0\u7063", "utc": 1426488609000, "level": 0, "avatar": "http://filestoresg1.beetalkmobile.com:8081/file/7756795050112755973", "name": "\u963f\u667a"}, "content": "\u9019\u90e8\u6211\u8a8d\u70ba\u662f\u7b2c\u4e8c\u500b\u704c\u7c43\u9ad8\u624b\uff0c\u4f60\u5011\u4e0d\u89ba\u5f97\u6bd4\u8cfd\u904e\u7a0b\u6bd4\u8f03\u8a73\u7d30\u4e14\u89d2\u8272\u98a8\u683c\u660e\u986f\uff0c\u53ef\u60dc\u7b2c\u4e8c\u90e8\u91cd\u8986\u6027\u592a\u9ad8\uff0c\u71b1\u60c5\u526950\uff05", "urls": [], "replies": {"first": [], "last": [], "noMoreReplies": true}, "images": [], "id": 5829939}, {"postBy": {"location": "\u65b0\u5317\u5e02\u00b7\u53f0\u7063", "utc": 1426613079000, "level": 0, "avatar": "http://filestoresg1.beetalkmobile.com:8081/file/-3141336605209548237", "name": "\u53c8\u5b85\u53c8\u521d\u3010 \u264d \u3011"}, "content": "\u597d\u770b \u2026\u2026\u2026\u2026", "urls": [], "replies": {"first": [], "last": [], "noMoreReplies": true}, "images": [], "id": 5943482}, {"postBy": {"location": "\u53f0\u5317\u5e02\u00b7\u53f0\u7063", "utc": 1426614245000, "level": 0, "avatar": "http://filestoresg1.beetalkmobile.com:8081/file/8769101112917436545", "name": "\u98df\u8089\u52d5\u7269"}, "content": "\u4e0d\u904e\u9ad8\u4e2d\u751f\u9a0epinarello dogma\u592a\u4e0d\u79d1\u5b78\u4e86.....", "urls": [], "replies": {"first": [], "last": [], "noMoreReplies": true}, "images": [], "id": 5944649}, {"postBy": {"location": "\u82d7\u6817\u7e23\u00b7\u53f0\u7063", "utc": 1426683633000, "level": 0, "avatar": "http://filestoresg1.beetalkmobile.com:8081/file/41470281282914645", "name": "\u5c0f\u6690"}, "content": "\u975e\u5e38\u597d\u770b\uff0c\u6bcf\u6b21\u770b\u5b8c\u4e00\u96c6\u90fd\u5f88\u671f\u5f85\u4e0b\u4e00\u96c6", "urls": [], "replies": {"first": [], "last": [], "noMoreReplies": true}, "images": [], "id": 5998127}, {"postBy": {"location": "\u65b0\u5317\u5e02\u00b7\u53f0\u7063", "utc": 1429886199000, "level": 0, "avatar": "http://filestoresg1.beetalkmobile.com:8081/file/6746137164885296888", "name": "\u5c0f\u9716"}, "content": "\u5168\u570b\u51a0\u8ecd\u554a", "urls": [], "replies": {"first": [], "last": [], "noMoreReplies": true}, "images": [], "id": 9636893}]}
