{"noMoreComments": true, "cursorEnd": 0, "id": "34301", "comments": [{"postBy": {"location": "", "utc": 1417230728000, "level": 0, "avatar": "http://filestoresg1.beetalkmobile.com:8081/file/1662787042511390416", "name": "\u5854\u5496\u5e7e\u5eb7"}, "content": "\u793e\u6703\u50f9\u503c\u89c0\u5d29\u58de<br /><br />", "urls": [], "replies": {"first": [], "last": [], "noMoreReplies": true}, "images": [], "id": 238671}, {"postBy": {"location": "\u5f70\u5316\u7e23\u00b7\u53f0\u7063", "utc": 1417231164000, "level": 0, "avatar": "http://filestoresg1.beetalkmobile.com:8081/file/8355363688450477048", "name": "hsker"}, "content": "\u50f9\u503c\u89c0\u5ff5\u554f\u984c", "urls": [], "replies": {"first": [], "last": [], "noMoreReplies": true}, "images": [], "id": 238711}, {"postBy": {"location": "Hualien County\u00b7Taiwan", "utc": 1417231211000, "level": 0, "avatar": "http://filestoresg1.beetalkmobile.com:8081/file/1333975887835489792", "name": "\u96b1\u85cf\u4eba\u7269"}, "content": "\u60f3\u8868\u9054\u4ec0\u9ebc\uff1f", "urls": [], "replies": {"first": [], "last": [], "noMoreReplies": true}, "images": [], "id": 238714}, {"postBy": {"location": "\u53f0\u5317\u5e02\u00b7\u53f0\u7063", "utc": 1417231212000, "level": 0, "avatar": "http://filestoresg1.beetalkmobile.com:8081/file/2584028250772796158", "name": "\u8001\u723a"}, "content": "\u6240\u4ee5\u2026", "urls": [], "replies": {"first": [], "last": [], "noMoreReplies": true}, "images": [], "id": 238715}, {"postBy": {"location": "Penghu County\u00b7Taiwan", "utc": 1417231975000, "level": 0, "avatar": "http://filestoresg1.beetalkmobile.com:8081/file/-2391234374351850428", "name": "\ud83c\udfef\u5edf\u5edf\ud83c\udfef"}, "content": "\u55ef\u55ef\u2026\u9019\u90fd\u5f88\u6b63\u5e38\u5440\uff01", "urls": [], "replies": {"first": [], "last": [], "noMoreReplies": true}, "images": [], "id": 238816}, {"postBy": {"location": "New Taipei City\u00b7Taiwan", "utc": 1417232130000, "level": 0, "avatar": "http://filestoresg1.beetalkmobile.com:8081/file/1364489539084201003", "name": "\u5634\u786c\u5fc3\u8edf-\u9189\u5c0f\u4e03"}, "content": "\u4e0d\u8981\u592a\u610f\u5916 \u4e45\u4e86\u6703\u7fd2\u6163", "urls": [], "replies": {"first": [], "last": [], "noMoreReplies": true}, "images": [], "id": 238829}, {"postBy": {"location": "\u65b0\u5317\u5e02\u00b7\u53f0\u7063", "utc": 1417232294000, "level": 0, "avatar": "http://filestoresg1.beetalkmobile.com:8081/file/380303486497594738", "name": "Oddschool"}, "content": "\u8aaa\u7684\u597d\uff0c\u53ea\u662f\u592a\u59d4\u5a49\u4e86\u3002", "urls": [], "replies": {"first": [], "last": [], "noMoreReplies": true}, "images": [], "id": 238847}, {"postBy": {"location": "\u5357\u5c6f\u5340\u00b7\u53f0\u7063", "utc": 1417232516000, "level": 0, "avatar": "http://filestoresg1.beetalkmobile.com:8081/file/-1878324299611300263", "name": "\ud83c\udf3a   Toby"}, "content": "\u96d6\u7136\u9019\u662f\u5927\u5bb6\u90fd\u77e5\u9053\u7684<br />\u4f46\u9084\u662f\u60f3\u807d\u8a73\u7d30\u7684\u5be6\u4f8b<br /><br /><br />\u4f8b\u5982\uff1a\u5167\u8932\u5e7e\u5929\u4e0d\u63db<br />\u6c92\u6d17\u6fa1\u5674\u9999\u6c34\uff1f<br />\u6216\u662f\u2026\u2026\uff1f", "urls": [], "replies": {"first": [{"content": "\u90a3\u4f60\u5167\u8932\u90fd\u5e7e\u5929\u624d\u63db\u554a\uff1f~~\u54c8~", "reply": "", "id": 168770, "name": "\u610f\u5916\u9047\u898b"}], "last": [{"content": "\u9001\u4f60\uff01", "reply": "\ud83c\udf3a   Toby", "id": 170295, "name": "Wen."}, {"content": "\u6211\u5abd\u8aaa~~~", "reply": "\u8001\u723a", "id": 170304, "name": "Wen."}], "noMoreReplies": false}, "images": [], "id": 238878}, {"postBy": {"location": "\u6843\u5712\u7e23\u00b7\u53f0\u7063", "utc": 1417236902000, "level": 0, "avatar": "http://filestoresg1.beetalkmobile.com:8081/file/-7880619848444046536", "name": "\u665a\u5b89\u5730\u7403\u4eba"}, "content": "\u793e\u4ea4\u901a\u5e38\u90fd\u662f\u5728\u507d\u88dd\u81ea\u5df1", "urls": [], "replies": {"first": [], "last": [], "noMoreReplies": true}, "images": [], "id": 239431}, {"postBy": {"location": "Taoyuan County\u00b7Taiwan", "utc": 1417241665000, "level": 0, "avatar": "http://filestoresg1.beetalkmobile.com:8081/file/6029247878761211576", "name": "\u6211\u53ea\u662f\u4e00\u7897\u62c9\u9eb5\ud83c\udf5c\ud83c\udf65"}, "content": "\u81ea\u5df1\u9078\u64c7\u7684", "urls": [], "replies": {"first": [], "last": [], "noMoreReplies": true}, "images": [], "id": 239962}, {"postBy": {"location": "\u53f0\u5317\u5e02\u00b7\u53f0\u7063", "utc": 1417242811000, "level": 0, "avatar": "http://filestoresg1.beetalkmobile.com:8081/file/3002185718318354390", "name": "dennis"}, "content": "\u9019\u793e\u6703\u5c31\u9019\u6a23", "urls": [], "replies": {"first": [], "last": [], "noMoreReplies": true}, "images": [], "id": 240113}, {"postBy": {"location": "\u65b0\u5317\u5e02\u00b7\u53f0\u7063", "utc": 1417243085000, "level": 0, "avatar": "http://filestoresg1.beetalkmobile.com:8081/file/-5144278451961918741", "name": "Wen."}, "content": "\u9084\u597d\u6211\u53ea\u8edf\u4eca\u5929", "urls": [], "replies": {"first": [{"content": "\u5230\u4e86\u660e\u5929\u5c0d\u4f60\u4f86\u8aaa\u9084\u662f\u4eca\u5929", "reply": "", "id": 169853, "name": "Dick"}], "last": [{"content": "\u54c8\u54c8\uff01\u5225\u5435\u5230\u4eba", "reply": "Wen.", "id": 170228, "name": "Dick"}, {"content": "\u5982\u679c\u4f60\u6c92\u52c7\u6c23\u966a\u6211\u5230~\u660e\u5929\u7684\u660e\u5929\u7684\u660e\u5929", "reply": "", "id": 170241, "name": "Wen."}], "noMoreReplies": false}, "images": [], "id": 240152}, {"postBy": {"location": "Kaohsiung City\u00b7Taiwan", "utc": 1417245576000, "level": 0, "avatar": "http://filestoresg1.beetalkmobile.com:8081/file/-9115981632762959030", "name": "\u73b2"}, "content": "\u662f\u554a\u2026\u2026\u9019\u5c31\u662f~\u4eba\u6027\u554a", "urls": [], "replies": {"first": [], "last": [], "noMoreReplies": true}, "images": [], "id": 240436}, {"postBy": {"location": "Taipei City\u00b7Taiwan", "utc": 1417247202000, "level": 0, "avatar": "http://filestoresg1.beetalkmobile.com:8081/file/-2352031288224133460", "name": "Dick"}, "content": "\u5176\u5be6\u4f60\u662f\u9760\u7537\u4eba\u751f\u6d3b\u7684\u3002\u56e0\u70ba\u9322\u662f\u7537\u4eba\u51fa\u7684", "urls": [], "replies": {"first": [{"content": "\u963f\u4e0d\u7136\u52d2\uff01\uff01\uff01\uff01\u4eba\u751f\u81ea\u53e4\u90fd\u99ac\u7537\u4eba\u51fa\uff01\uff01\uff01", "reply": "", "id": 170317, "name": "Wen."}, {"content": "\u4e0d\u7136\u600e\u9ebc\u5831\u570b", "reply": "", "id": 170320, "name": "Wen."}], "last": [], "noMoreReplies": true}, "images": [], "id": 240641}]}
