{"noMoreComments": true, "cursorEnd": 0, "id": "152930", "comments": [{"postBy": {"location": "\u5609\u7fa9\u5e02\u00b7\u53f0\u7063", "utc": 1419626339000, "level": 0, "avatar": "http://filestoresg1.beetalkmobile.com:8081/file/-8247883117297039809", "name": "\u661f\u54a9"}, "content": "\u5df2\u7d93\u5f88\u597d\u4e86\u554a", "urls": [], "replies": {"first": [{"content": "\u54c8\u54c8\n\u8b1d\u8b1d~", "reply": "", "id": 742051, "name": "\u881f\u7b46\u5c0f\u8208"}], "last": [], "noMoreReplies": true}, "images": [], "id": 1024874}]}
